Workbook

Sheet Source Pass Summary
A1: Monstare Evidence Matrix - Source Location Pass v2
A2: Date | B2: 2026-08-13
A3: Scope | B3: Completed another source-location pass on remaining Priority A rows; after all A rows had a located source or access path, initiated Priority B pass through core theory + philosophy/QS rows.
A4: Priority A outcome | B4: All remaining Priority A rows now have a readable URL, restricted but legal access path, or authoritative landing/source path recorded.
A5: Priority B outcome | B5: Priority B started: core rows and Area 1/Area 2 early cluster updated where sources were found in this pass. Remaining B rows are left queued for the next pass.
A6: Halting principle | B6: Stopped after A completion plus a coherent B tranche, rather than forcing weak/unverified links into the matrix. Rows with landing-only/restricted access are clearly marked.
A7: Quality law | B7: Citation is still not evidence. Rows are source-located, not charted, until findings/effects/limits/disconfirmation are completed.
A8: Rows updated | B8: 77
A10: PATCH UPDATE v3
A11: Patch date | B11: 2026-08-13
A12: Additive additions | B12: 38 previously queued/missing rows source-located; 5 staleness columns added.
A13: Subtractions | B13: None. No evidence rows, existing source URLs, comments, or formulas intentionally removed.
A14: Quality law | B14: Source-located does not mean charted; findings/effects/limits/disconfirmation still require charting.

Sheet Guide & Legend
A1: MONSTARE EVIDENCE MATRIX
A2: Rev 5 schema | Stage 3 charting instrument | Prepared for Dallas by Pip, with Locus/Council logic | 12 Aug 2026
A4: PURPOSE
A5: This workbook is the Evidence Matrix called for in the Rev 5 research plan and the Version 2 execution plan.
A6: It converts the integrated source architecture (Rev 5 Section 3B, the ten areas) into a chartable database.
A7: The 'Evidence Matrix' sheet is SEEDED: descriptive/mapping columns are pre-filled from the plan; evidential
A8: columns are left as [to chart] so charting still happens per source. Council rule: citation is not evidence.
A10: HOW TO USE (Stage 3 charting)
A11: 1. Work top-to-bottom in the Rev 5 priority reading order (Phase 1 first: rows tagged Priority A in Areas 1,2,3,6).
A12: 2. For each source, retrieve it, then fill the [to chart] cells: Key Finding, Effect Size, Limitations, Disconfirming.
A13: 3. Set Verification Status to 'Verified' once the DOI/citation is confirmed (Section 4.6 discipline).
A14: 4. A source is not 'charted' until columns L-O are complete AND Verification = Verified.
... A29: KEYS
A30: PRIORITY | B30: A = load-bearing (chart early) | B = strong supporting | C = contextual / bridge
A31: FUNCTION | B31: TELOS defines purpose | MECHANISM how it works | WARNING failure modes | METHOD procedure | DESIGN artifact guidance | MEASURE operationalization | CRITIQUE challenges assumptions
A32: AREAS 1-10 | B32: 1 Philosophy of tech beyond Hui | 2 Personal informatics/QS critique | 3 Critical HCI agency/moral friction | 4 Environmental psych place/restoration | 5 Phenomenological methods | 6 Automation ethics/autonomy | 7 AI offloading/self-regulation | 8 Ritual/symbolic practice | 9 Work productivity ecology | 10 Cross-cultural autonomy/technodiversity
A33: FAILURE MODES | B33: CF-1 productivity without moral gain | CF-2 metric capture | CF-3 internalized coercion | CF-4 tech paternalism | CF-5 attentional extraction | CF-6 ecological flattening | CF-7 ritual hollowing | CF-8 universalization | CF-9 reversibility loss | CF-10 false cosmotechnics
A34: WORKSTREAMS | B34: WS-A Motivation | WS-B Willpower/structure | WS-C Emotion regulation | WS-D Behavioral diagnosis | WS-E Environmental ecology | WS-F Phenomenology | WS-G Reference/consequence | WS-H Digital/temporal | WS-I Adverse effects | WS-J Moderators | WS-K Cosmotechnics | WS-L Moral ecology
A36: SOURCE DISCOVERY UPDATE v1
A37: Eight columns were added to Evidence Matrix: Readable Source URL, Source Landing URL, Access Type, Source Discovery Status, Discovery Notes, Suggested Search Query, Scholar/Web Search URL, and Source Checked Date. Direct links were added only where discovered in this first pass; all other rows are queued and not verified.

Sheet Source Discovery Log
A1: Field | B1: Value
A2: Run purpose | B2: First-pass readable-source locator to make future context-window handoffs easier.
A3: Run date | B3: 2026-08-13
A4: Rows with direct readable source added | B4: 13
A5: Companion Hui 2024 row added | B5: Yes, as HUI-2024, because it materially grounds the v6 design memo.
A6: Default for unsearched rows | B6: Queued with suggested web query; not marked verified.
A7: Charting rule preserved | B7: A row is not charted until evidential notes are completed and verification is confirmed.
A8: Next recommended search pass | B8: Continue Priority A rows in Areas 1, 2, 3, 6, then core motivation/method sources.

Sheet Dashboard
A1: MONSTARE EVIDENCE MATRIX — DASHBOARD
A2: Live counts recalculated from the Evidence Matrix sheet. Charting progress = Verified rows.
A4: TOTALS | F4: COSMOTECHNIC RELEVANCE
A5: Total sources | B5: =COUNTA('Evidence Matrix'!A2:A129) -> 128 | F5: Level | H5: Count
A6: Priority A (load-bearing) | B6: =COUNTIF('Evidence Matrix'!F2:F129,"A") -> 0 | F6: high | H6: =COUNTIF('Evidence Matrix'!K2:K129,"high") -> 0
A7: Priority B | B7: =COUNTIF('Evidence Matrix'!F2:F129,"B") -> 0 | F7: medium | H7: =COUNTIF('Evidence Matrix'!K2:K129,"medium") -> 0
A8: Priority C | B8: =COUNTIF('Evidence Matrix'!F2:F129,"C") -> 0 | F8: low | H8: =COUNTIF('Evidence Matrix'!K2:K129,"low") -> 0
A9: Verified (charted) | B9: =COUNTIF('Evidence Matrix'!C2:C129,"Verified") -> 0
A10: Pending | B10: =COUNTIF('Evidence Matrix'!C2:C129,"Pending") -> 0
A11: % charted | B11: =IF(B5=0,0,B9/B5) -> 0
A13: BY SOURCE AREA (1-10) | F13: BY WORKSTREAM
A14: Area | B14: Description | C14: Sources | D14: Verified | F14: WS | G14: Focus | H14: Sources
A15: 1 | B15: Philosophy of technology beyond Hui | C15: =COUNTIF('Evidence Matrix'!D2:D129,1) -> 0 | D15: =COUNTIFS('Evidence Matrix'!D2:D129,1,'Evidence Matrix'!C2:C129,"Verified") -> 0 | F15: WS-A | G15: Motivational quality | H15: =COUNTIF('Evidence Matrix'!E2:E129,"WS-A") -> 0
A16: 2 | B16: Personal informatics / QS critique | C16: =COUNTIF('Evidence Matrix'!D2:D129,2) -> 0 | D16: =COUNTIFS('Evidence Matrix'!D2:D129,2,'Evidence Matrix'!C2:C129,"Verified") -> 0 | F16: WS-B | G16: Willpower / structure | H16: =COUNTIF('Evidence Matrix'!E2:E129,"WS-B") -> 0
A17: 3 | B17: Critical HCI: agency & moral friction | C17: =COUNTIF('Evidence Matrix'!D2:D129,3) -> 0 | D17: =COUNTIFS('Evidence Matrix'!D2:D129,3,'Evidence Matrix'!C2:C129,"Verified") -> 0 | F17: WS-C | G17: Emotion regulation | H17: =COUNTIF('Evidence Matrix'!E2:E129,"WS-C") -> 0
A18: 4 | B18: Environmental psychology: place & restoration | C18: =COUNTIF('Evidence Matrix'!D2:D129,4) -> 0 | D18: =COUNTIFS('Evidence Matrix'!D2:D129,4,'Evidence Matrix'!C2:C129,"Verified") -> 0 | F18: WS-D | G18: Behavioral diagnosis | H18: =COUNTIF('Evidence Matrix'!E2:E129,"WS-D") -> 0
A19: 5 | B19: Phenomenological methods | C19: =COUNTIF('Evidence Matrix'!D2:D129,5) -> 0 | D19: =COUNTIFS('Evidence Matrix'!D2:D129,5,'Evidence Matrix'!C2:C129,"Verified") -> 0 | F19: WS-E | G19: Environmental ecology | H19: =COUNTIF('Evidence Matrix'!E2:E129,"WS-E") -> 0
A20: 6 | B20: Automation ethics & autonomy | C20: =COUNTIF('Evidence Matrix'!D2:D129,6) -> 0 | D20: =COUNTIFS('Evidence Matrix'!D2:D129,6,'Evidence Matrix'!C2:C129,"Verified") -> 0 | F20: WS-F | G20: Phenomenology | H20: =COUNTIF('Evidence Matrix'!E2:E129,"WS-F") -> 0
A21: 7 | B21: AI offloading & self-regulation | C21: =COUNTIF('Evidence Matrix'!D2:D129,7) -> 0 | D21: =COUNTIFS('Evidence Matrix'!D2:D129,7,'Evidence Matrix'!C2:C129,"Verified") -> 0 | F21: WS-G | G21: Reference / consequence | H21: =COUNTIF('Evidence Matrix'!E2:E129,"WS-G") -> 0
A22: 8 | B22: Ritual & symbolic practice | C22: =COUNTIF('Evidence Matrix'!D2:D129,8) -> 0 | D22: =COUNTIFS('Evidence Matrix'!D2:D129,8,'Evidence Matrix'!C2:C129,"Verified") -> 0 | F22: WS-H | G22: Digital / temporal | H22: =COUNTIF('Evidence Matrix'!E2:E129,"WS-H") -> 0
A23: 9 | B23: Work productivity ecology | C23: =COUNTIF('Evidence Matrix'!D2:D129,9) -> 0 | D23: =COUNTIFS('Evidence Matrix'!D2:D129,9,'Evidence Matrix'!C2:C129,"Verified") -> 0 | F23: WS-I | G23: Adverse effects | H23: =COUNTIF('Evidence Matrix'!E2:E129,"WS-I") -> 0
A24: 10 | B24: Cross-cultural autonomy & technodiversity | C24: =COUNTIF('Evidence Matrix'!D2:D129,10) -> 0 | D24: =COUNTIFS('Evidence Matrix'!D2:D129,10,'Evidence Matrix'!C2:C129,"Verified") -> 0 | F24: WS-J | G24: Moderators | H24: =COUNTIF('Evidence Matrix'!E2:E129,"WS-J") -> 0
A25: core+methods | B25: Carried core theory & methods (Rev 3-4) | C25: =B5-SUM(C15:C24) -> 128 | D25: =COUNTIF('Evidence Matrix'!C2:C129,"Verified")-SUM(D15:D24) -> 0 | F25: WS-K | G25: Cosmotechnics | H25: =COUNTIF('Evidence Matrix'!E2:E129,"WS-K") -> 0
F26: WS-L | G26: Moral ecology | H26: =COUNTIF('Evidence Matrix'!E2:E129,"WS-L") -> 0

Sheet Evidence Matrix
A1: ID | B1: Citation | C1: Readable Source URL | D1: Source Landing URL | E1: Access Type | F1: Source Discovery Status | G1: Discovery Notes | H1: Suggested Search Query | I1: Scholar/Web Search URL | J1: Source Checked Date | K1: Verif. | L1: Area | M1: WS | N1: Pri | O1: Function | P1: Evidence Type | Q1: Domain | R1: Causal Status | S1: Cosmo Rel. | T1: Key Finding / Thesis | U1: Effect Size / Strength | V1: Limitations | W1: Disconfirming Implication | X1: H1 | Y1: H2 | Z1: Design Implication | AA1: Cosmotechnic Implication | AB1: Fail Mode | AC1: Artifact Affected | AD1: Open Charge | AE1: Staleness Domain | AF1: Re-search Interval | AG1: Last Verified Date | AH1: Re-search By | AI1: Staleness Status
A2: CORE-01 | B2: Ryan & Deci — Self-Determination Theory (needs) | C2: https://selfdeterminationtheory.org/SDT/documents/2000_RyanDeci_SDT.pdf | D2: https://selfdeterminationtheory.org/theory/ | E2: Open PDF / alternate SDT primary paper | F2: Readable source found - verify exact intended source before charting | G2: Matrix row names the SDT needs construct broadly. This link is Ryan & Deci 2000 SDT overview; exact 2017 book is also discoverable but not necessarily legally open in full. Use this as an accessible primary anchor unless the project requires the 2017 Guilford book. | H2: Ryan & Deci — Self-Determination Theory (needs) pdf DOI readable source | I2: https://www.google.com/search?q=Ryan+%26+Deci+%E2%80%94+Self-Determination+Theory+%28needs%29+pdf+DOI+readable+source | J2: 2026-08-13 | K2: Pending | L2: core | M2: WS-A | N2: A | O2: TELOS/MECHANISM | P2: theoretical | Q2: motivation | R2: conceptual | S2: high | T2: Autonomy, competence, relatedness convert pressure into durable, autonomous motivation. | U2: [to chart] | V2: [to chart] | W2: [to chart] | X2: yes | Y2: yes | Z2: Ground the need-support profile (M2); define autonomous vs controlled motivation. | AA2: Motivation quality is the substrate of moral authorship, not just output. | AB2: CF-3 | AC2: Agency & Autonomy Checklist | AD2: OC-8 | AE2: General supporting source | AF2: 36 months | AG2: 2026-08-13 | AH2: 2029-08-13 | AI2: Current - re-search on schedule
A3: CORE-02 | B3: Markland, Ryan, Tobin & Rollnick — MI + SDT | C3: https://selfdeterminationtheory.org/SDT/documents/2005_MarklandRyanTobinRollnick_MotivationalInterviewing.pdf | D3: https://pure.ewha.ac.kr/en/publications/motivational-interviewing-and-self-determination-theory/ | E3: Open PDF | F3: Readable source found | G3: DOI identified in search result as 10.1521/jscp.2005.24.6.811. | H3: Markland, Ryan, Tobin & Rollnick — MI + SDT pdf DOI readable source | I3: https://www.google.com/search?q=Markland%2C+Ryan%2C+Tobin+%26+Rollnick+%E2%80%94+MI+%2B+SDT+pdf+DOI+readable+source | J3: 2026-08-13 | K3: Pending | L3: core | M3: WS-A | N3: A | O3: MECHANISM | P3: theoretical | Q3: motivation | R3: conceptual | S3: medium | T3: MI is a social-environmental support for autonomy and internalization. | U3: [to chart] | V3: [to chart] | W3: [to chart] | X3: yes | Y3: partial | Z3: Autonomy-preserving conversational method for ambivalence. | AA3: Non-coercive change as cosmotechnic constraint. | AB3: CF-3 | AC3: Self-Nudging Design Card | AE3: General supporting source | AF3: 36 months | AG3: 2026-08-13 | AH3: 2029-08-13 | AI3: Current - re-search on schedule
A4: CORE-03 | B4: Vansteenkiste, Williams & Resnicow — SDT/MI integration | C4: https://selfdeterminationtheory.org/wp-content/uploads/2014/04/2012_VansteenkisteWilliamsResnicow_InterventionDevelopment_IJBNPA.pdf | D4: https://link.springer.com/article/10.1186/1479-5868-9-23 | E4: Open PDF | F4: Located - readable source | G4: Priority B pass: open PDF located via SDT repository; Springer landing recorded. | H4: Vansteenkiste, Williams & Resnicow — SDT/MI integration pdf DOI readable source | I4: https://www.google.com/search?q=Vansteenkiste%2C+Williams+%26+Resnicow+%E2%80%94+SDT%2FMI+integration+pdf+DOI+readable+source | J4: 2026-08-13 | K4: Located (not charted) | L4: core | M4: WS-A | N4: B | O4: MECHANISM | P4: review | Q4: motivation | R4: conceptual | S4: medium | T4: Autonomy/volition is the shared process principle across SDT and MI. | U4: [to chart] | V4: [to chart] | W4: [to chart] | X4: yes | Y4: partial | Z4: Unify motivational method around volition. | AA4: Volition over compliance. | AB4: CF-3 | AC4: Self-Nudging Design Card | AE4: Empirical / applied research | AF4: 24 months | AG4: 2026-08-13 | AH4: 2028-08-13 | AI4: Current - re-search on schedule
A5: CORE-04 | B5: Bandura — Self-efficacy | C5: https://www.uky.edu/~eushe2/Bandura/Bandura1997SE.pdf | D5: https://psycnet.apa.org/record/1997-08589-000 | E5: Open PDF / landing | F5: Located - readable source | G5: PDF located for Bandura self-efficacy book excerpt/chapter. Verify edition/page details during charting. | H5: Bandura — Self-efficacy pdf DOI readable source | I5: https://www.google.com/search?q=Bandura+%E2%80%94+Self-efficacy+pdf+DOI+readable+source | J5: 2026-08-13 | K5: Located (not charted) | L5: core | M5: WS-A | N5: A | O5: MECHANISM | P5: theoretical | Q5: motivation | R5: causal | S5: medium | T5: Domain-specific efficacy; mastery is the strongest source; reciprocal with performance. | U5: [to chart] | V5: [to chart] | W5: [to chart] | X5: yes | Y5: partial | Z5: Build efficacy via early mastery, not exhortation (M2). | AA5: Competence as capacity for good action. | AC5: Motivation Crowding Watch Card | AE5: General supporting source | AF5: 36 months | AG5: 2026-08-13 | AH5: 2029-08-13 | AI5: Current - re-search on schedule
A6: CORE-05 | B6: Deci, Koestner & Ryan — extrinsic rewards meta-analysis | C6: https://selfdeterminationtheory.org/wp-content/uploads/2014/04/1999_DeciKoestnerRyan_Meta.pdf | D6: https://doi.org/10.1037/0033-2909.125.6.627 | E6: Open PDF | F6: Readable source found | G6: Search results report meta-analysis of 128 studies and DOI 10.1037/0033-2909.125.6.627. | H6: Deci, Koestner & Ryan — extrinsic rewards meta-analysis pdf DOI readable source | I6: https://www.google.com/search?q=Deci%2C+Koestner+%26+Ryan+%E2%80%94+extrinsic+rewards+meta-analysis+pdf+DOI+readable+source | J6: 2026-08-13 | K6: Pending | L6: core | M6: WS-I | N6: A | O6: WARNING | P6: review | Q6: motivation | R6: causal | S6: high | T6: Contingent tangible rewards undermine intrinsic motivation; positive feedback enhances. | U6: [to chart] | V6: [to chart] | W6: [to chart] | X6: yes | Y6: yes | Z6: Core H1c crowding evidence; sets c_C in the model. | AA6: Buying compliance can cost autonomy = cosmotechnic failure. | AB6: CF-1/CF-3 | AC6: Motivation Crowding Watch Card | AD6: OC-2 | AE6: Empirical / applied research | AF6: 24 months | AG6: 2026-08-13 | AH6: 2028-08-13 | AI6: Current - re-search on schedule
A7: CORE-06 | B7: Frey & Jegen — motivation crowding theory | C7: https://www.bsfrey.ch/articles/C_317_01.pdf | D7: https://doi.org/10.1023/A:1017564312479 | E7: Open PDF / DOI landing | F7: Located - readable source | G7: Readable author PDF located for motivation crowding theory. | H7: Frey & Jegen — motivation crowding theory pdf DOI readable source | I7: https://www.google.com/search?q=Frey+%26+Jegen+%E2%80%94+motivation+crowding+theory+pdf+DOI+readable+source | J7: 2026-08-13 | K7: Located (not charted) | L7: core | M7: WS-I | N7: A | O7: WARNING | P7: review | Q7: economics/psych | R7: correlational | S7: high | T7: External incentives can crowd out intrinsic motivation (crowding-out effect). | U7: [to chart] | V7: [to chart] | W7: [to chart] | X7: yes | Y7: yes | Z7: Cross-disciplinary confirmation of crowding risk. | AA7: Incentive design is morally consequential. | AB7: CF-1/CF-3 | AC7: Motivation Crowding Watch Card | AD7: OC-2 | AE7: Empirical / applied research | AF7: 24 months | AG7: 2026-08-13 | AH7: 2028-08-13 | AI7: Current - re-search on schedule
A8: CORE-07 | B8: Lepper, Greene & Nisbett — over-justification | C8: https://selfdeterminationtheory.org/SDT/documents/1973_LepperGreeneNisbett.pdf | D8: https://psycnet.apa.org/doi/10.1037/h0035519 | E8: Open PDF / DOI landing | F8: Located - readable source | G8: Readable SDT archive PDF for classic overjustification paper. | H8: Lepper, Greene & Nisbett — over-justification pdf DOI readable source | I8: https://www.google.com/search?q=Lepper%2C+Greene+%26+Nisbett+%E2%80%94+over-justification+pdf+DOI+readable+source | J8: 2026-08-13 | K8: Located (not charted) | L8: core | M8: WS-I | N8: A | O8: WARNING | P8: empirical | Q8: psychology | R8: causal | S8: high | T8: Expected reward for intrinsically interesting activity reduces later interest. | U8: [to chart] | V8: [to chart] | W8: [to chart] | X8: yes | Y8: partial | Z8: Original demonstration; anchors the tip-over intuition. | AA8: Reward can hollow meaning. | AB8: CF-3 | AC8: Motivation Crowding Watch Card | AE8: Empirical / applied research | AF8: 24 months | AG8: 2026-08-13 | AH8: 2028-08-13 | AI8: Current - re-search on schedule
A9: CORE-08 | B9: Reijula & Hertwig — self-nudging & citizen choice architect | C9: https://nudging-for-sdgs.eu/wp-content/uploads/2023/12/Self-nudging-and-the-citizen-choice-architect.pdf | D9: https://researchportal.helsinki.fi/en/publications/self-nudging-and-the-citizen-choice-architect | E9: Open PDF / publisher or postprint also available | F9: Readable source found | G9: Search results identify DOI 10.1017/bpp.2020.5 and OSF DOI 10.31235/osf.io/24dwn. | H9: Reijula & Hertwig — self-nudging & citizen choice architect pdf DOI readable source | I9: https://www.google.com/search?q=Reijula+%26+Hertwig+%E2%80%94+self-nudging+%26+citizen+choice+architect+pdf+DOI+readable+source | J9: 2026-08-13 | K9: Pending | L9: core | M9: WS-D | N9: A | O9: DESIGN/MECHANISM | P9: theoretical | Q9: behavioral policy | R9: conceptual | S9: high | T9: The person as choice-architect of their own proximal environment preserves internal PLOC. | U9: [to chart] | V9: [to chart] | W9: [to chart] | X9: yes | Y9: yes | Z9: Central mechanism for authorship (lambda); M4d. | AA9: Self-authorship as vehicle for autonomy, but not sufficient. | AB9: CF-3 | AC9: Self-Nudging Design Card | AD9: OC-6 | AE9: General supporting source | AF9: 36 months | AG9: 2026-08-13 | AH9: 2029-08-13 | AI9: Current - re-search on schedule
A10: CORE-09 | B10: Carver & Scheier — self-regulation / control theory | C10: https://stuff.mit.edu/afs/athena/course/9/9.00/readings/CarverScheier1982.pdf | D10: https://doi.org/10.1037/0033-295X.89.2.111 | E10: Open PDF / DOI landing | F10: Located - readable source | G10: Readable PDF of feedback/self-regulation control theory located. | H10: Carver & Scheier — self-regulation / control theory pdf DOI readable source | I10: https://www.google.com/search?q=Carver+%26+Scheier+%E2%80%94+self-regulation+%2F+control+theory+pdf+DOI+readable+source | J10: 2026-08-13 | K10: Located (not charted) | L10: core | M10: WS-G | N10: A | O10: MECHANISM | P10: theoretical | Q10: psychology | R10: conceptual | S10: medium | T10: Behavior is a feedback loop: input, comparator vs reference, output, environment. | U10: [to chart] | V10: [to chart] | W10: [to chart] | X10: yes | Y10: partial | Z10: Loop design (M4b); feedback quality is the lever. | AA10: Loops encode values; what they make salient matters. | AC10: Arousal/Flow/Task-Switching Layer | AD10: OC-4 | AE10: Empirical / applied research | AF10: 24 months | AG10: 2026-08-13 | AH10: 2028-08-13 | AI10: Current - re-search on schedule
A11: CORE-10 | B11: Locke & Latham — goal-setting theory | C11: https://home.ubalt.edu/tmitch/642/Articles%20syllabus/Locke%20Latham%202002%20building%20theory%20goal%20setting%20Am%20Psych.pdf | D11: https://psycnet.apa.org/record/2002-10108-003 | E11: Open PDF / landing | F11: Located - readable source | G11: Readable PDF for Locke & Latham goal-setting theory article located. | H11: Locke & Latham — goal-setting theory pdf DOI readable source | I11: https://www.google.com/search?q=Locke+%26+Latham+%E2%80%94+goal-setting+theory+pdf+DOI+readable+source | J11: 2026-08-13 | K11: Located (not charted) | L11: core | M11: WS-G | N11: A | O11: MECHANISM | P11: review | Q11: org psych | R11: causal | S11: medium | T11: Specific/difficult goals beat 'do your best' via four mechanisms, five moderators. | U11: [to chart] | V11: [to chart] | W11: [to chart] | X11: yes | Y11: partial | Z11: Reference-setting (M4a); learning vs performance framing. | AA11: Goals must be morally/ecologically fit, not just efficient. | AB11: CF-1 | AC11: Monstare Protocol vNext | AE11: Empirical / applied research | AF11: 24 months | AG11: 2026-08-13 | AH11: 2028-08-13 | AI11: Current - re-search on schedule
A12: CORE-11 | B12: Ordonez et al. — Goals Gone Wild | C12: https://www.hbs.edu/ris/Publication%20Files/09-083.pdf | D12: https://www.jstor.org/stable/27747490 | E12: Open PDF / JSTOR landing | F12: Located - readable source | G12: Priority B pass: HBS working paper PDF and JSTOR landing located. | H12: Ordonez et al. — Goals Gone Wild pdf DOI readable source | I12: https://www.google.com/search?q=Ordonez+et+al.+%E2%80%94+Goals+Gone+Wild+pdf+DOI+readable+source | J12: 2026-08-13 | K12: Located (not charted) | L12: core | M12: WS-G | N12: B | O12: WARNING | P12: review | Q12: org psych | R12: conceptual | S12: medium | T12: Aggressive goals cause narrowing, stress, shortcuts, reduced intrinsic interest. | U12: [to chart] | V12: [to chart] | W12: [to chart] | X12: partial | Y12: yes | Z12: Goal failure modes; guardrails on M4a. | AA12: Goal narrowing as moral flattening. | AB12: CF-1 | AC12: Design Veto Catalogue | AE12: Empirical / applied research | AF12: 24 months | AG12: 2026-08-13 | AH12: 2028-08-13 | AI12: Current - re-search on schedule
A13: CORE-12 | B13: Ferster & Skinner — Schedules of Reinforcement | C13: https://archive.org/details/schedulesofreinf0000fers | D13: https://www.worldcat.org/title/191941 | E13: Archive lending / catalog landing | F13: Located - restricted readable | G13: Archive lending page located; no stable open full text found in pass. | H13: Ferster & Skinner — Schedules of Reinforcement pdf DOI readable source | I13: https://www.google.com/search?q=Ferster+%26+Skinner+%E2%80%94+Schedules+of+Reinforcement+pdf+DOI+readable+source | J13: 2026-08-13 | K13: Located (not charted) | L13: core | M13: WS-G | N13: A | O13: MECHANISM | P13: empirical | Q13: behavior analysis | R13: causal | S13: medium | T13: Variable-ratio schedules are most extinction-resistant. | U13: [to chart] | V13: [to chart] | W13: [to chart] | X13: yes | Y13: no | Z13: Contingency/schedule design (M4c). | AA13: Slot-machine schedules risk dependency. | AB13: CF-3 | AC13: Design Veto Catalogue | AE13: Empirical / applied research | AF13: 24 months | AG13: 2026-08-13 | AH13: 2028-08-13 | AI13: Current - located, access/fit caveat
A14: CORE-13 | B14: Staddon & Cerutti — operant conditioning review | C14: https://pmc.ncbi.nlm.nih.gov/articles/PMC1473025/ | D14: https://scholars.duke.edu/publication/915302 | E14: Open full text / DOI landing | F14: Located - readable source | G14: Priority B pass: PMC full text for Annual Review chapter located. | H14: Staddon & Cerutti — operant conditioning review pdf DOI readable source | I14: https://www.google.com/search?q=Staddon+%26+Cerutti+%E2%80%94+operant+conditioning+review+pdf+DOI+readable+source | J14: 2026-08-13 | K14: Located (not charted) | L14: core | M14: WS-G | N14: B | O14: MECHANISM/REVIEW | P14: review | Q14: behavior analysis | R14: causal | S14: low | T14: Matching law; consequence-engineering is neither simple nor cost-free. | U14: [to chart] | V14: [to chart] | W14: [to chart] | X14: yes | Y14: no | Z14: Temper naive contingency design. | AA14: Consequence engineering has hidden costs. | AB14: CF-3 | AC14: Motivation Crowding Watch Card | AE14: Empirical / applied research | AF14: 24 months | AG14: 2026-08-13 | AH14: 2028-08-13 | AI14: Current - re-search on schedule
A15: CORE-14 | B15: Clark & Chalmers — The Extended Mind | C15: https://consc.net/papers/extended.html | D15: https://doi.org/10.1093/019823682X.003.0002 | E15: Author HTML / DOI landing | F15: Located - readable source | G15: Readable author version located for The Extended Mind. | H15: Clark & Chalmers — The Extended Mind pdf DOI readable source | I15: https://www.google.com/search?q=Clark+%26+Chalmers+%E2%80%94+The+Extended+Mind+pdf+DOI+readable+source | J15: 2026-08-13 | K15: Located (not charted) | L15: core | M15: WS-E | N15: A | O15: TELOS | P15: philosophical | Q15: cognitive science | R15: conceptual | S15: high | T15: Cognition is partly constituted by body, tools, and environment. | U15: [to chart] | V15: [to chart] | W15: [to chart] | X15: partial | Y15: yes | Z15: Warrant for treating environment design as cognitive design. | AA15: Cognitive design is also world-design. | AC15: Digital Capture Architecture | AE15: Philosophical / historical / theoretical | AF15: 60 months | AG15: 2026-08-13 | AH15: 2031-08-13 | AI15: Current - re-search on schedule
A16: CORE-15 | B16: Gross — emotion regulation timeline | C16: https://spl.stanford.edu/pdfs/1998%20Gross%20-%20The%20Emerging%20Field%20of%20Emotion%20Regulation.pdf | D16: https://doi.org/10.1037/1089-2680.2.3.271 | E16: Open PDF / DOI landing | F16: Located - readable source | G16: Readable PDF located for Gross emotion regulation review. | H16: Gross — emotion regulation timeline pdf DOI readable source | I16: https://www.google.com/search?q=Gross+%E2%80%94+emotion+regulation+timeline+pdf+DOI+readable+source | J16: 2026-08-13 | K16: Located (not charted) | L16: core | M16: WS-C | N16: A | O16: MECHANISM | P16: theoretical | Q16: affective science | R16: causal | S16: medium | T16: Antecedent regulation (situation selection/modification) is cheaper than response repair. | U16: [to chart] | V16: [to chart] | W16: [to chart] | X16: yes | Y16: partial | Z16: Locate intervention point (M3); antecedent design. | AA16: Regulation without numbing meaningful signals. | AC16: Monstare Protocol vNext | AE16: General supporting source | AF16: 36 months | AG16: 2026-08-13 | AH16: 2029-08-13 | AI16: Current - re-search on schedule
A17: CORE-16 | B17: Csikszentmihalyi — Flow | C17: https://archive.org/details/flowpsychologyof0000csik | D17: https://www.harpercollins.com/products/flow-mihaly-csikszentmihalyi | E17: Archive lending / publisher landing | F17: Located - restricted readable | G17: Archive lending and publisher page located; charting should use borrowed/legal copy. | H17: Csikszentmihalyi — Flow pdf DOI readable source | I17: https://www.google.com/search?q=Csikszentmihalyi+%E2%80%94+Flow+pdf+DOI+readable+source | J17: 2026-08-13 | K17: Located (not charted) | L17: core | M17: WS-E | N17: A | O17: MECHANISM | P17: theoretical | Q17: psychology | R17: conceptual | S17: medium | T17: Challenge-skill balance, clear goals, feedback yield absorbed engagement. | U17: [to chart] | V17: [to chart] | W17: [to chart] | X17: yes | Y17: partial | Z17: Conditions suppliable; state not forceable. | AA17: Flow as attunement, not extraction. | AC17: Arousal/Flow/Task-Switching Layer | AE17: Empirical / applied research | AF17: 24 months | AG17: 2026-08-13 | AH17: 2028-08-13 | AI17: Current - located, access/fit caveat
A18: CORE-17 | B18: Kazdin — Single-Case Research Designs | C18: https://archive.org/details/singlecaseresear00alan | D18: https://books.google.com/books/about/Single_Case_Research_Designs.html?id=RvrTEQAAQBAJ | E18: Borrow/controlled digital lending or book preview | F18: Readable source located - access controlled | G18: Exact edition may vary. Archive link is 1982 access-restricted scan; Google Books entry shows later third edition. Treat as access-controlled book, not open article. | H18: Kazdin — Single-Case Research Designs pdf DOI readable source | I18: https://www.google.com/search?q=Kazdin+%E2%80%94+Single-Case+Research+Designs+pdf+DOI+readable+source | J18: 2026-08-13 | K18: Pending | L18: methods | M18: methods | N18: A | O18: METHOD | P18: methods | Q18: research methods | R18: conceptual | S18: low | T18: Multiple-baseline logic controls history/maturation without a control person. | U18: [to chart] | V18: [to chart] | W18: [to chart] | X18: partial | Y18: no | Z18: Spine of the Tier-C pilot (SCED). | AA18: Rigorous N-of-1 inference vs false generalization. | AC18: SCED Phase Plan | AD18: OC-5 | AE18: Methods / reporting standards | AF18: 36 months | AG18: 2026-08-13 | AH18: 2029-08-13 | AI18: Current - re-search on schedule
A19: CORE-18 | B19: Tate et al. — SCRIBE 2016 reporting guideline | C19: https://www.equator-network.org/reporting-guidelines/scribe-statement/ | D19: https://academic.oup.com/ptj/article/96/7/e1/2864911 | E19: Open guideline page / article page / checklist PDF | F19: Readable source found | G19: EQUATOR page supplies full bibliographic reference, links, and the 26-item SCRIBE 2016 guideline. | H19: Tate et al. — SCRIBE 2016 reporting guideline pdf DOI readable source | I19: https://www.google.com/search?q=Tate+et+al.+%E2%80%94+SCRIBE+2016+reporting+guideline+pdf+DOI+readable+source | J19: 2026-08-13 | K19: Pending | L19: methods | M19: methods | N19: A | O19: METHOD | P19: methods | Q19: research methods | R19: conceptual | S19: low | T19: 26-item checklist for single-case behavioral intervention reporting. | U19: [to chart] | V19: [to chart] | W19: [to chart] | X19: partial | Y19: no | Z19: Governs SCED reporting quality. | AA19: Transparency as anti-self-deception. | AC19: Preregistration Packet | AD19: OC-5 | AE19: Methods / reporting standards | AF19: 36 months | AG19: 2026-08-13 | AH19: 2029-08-13 | AI19: Current - re-search on schedule
A20: CORE-19 | B20: Klasnja et al. — Micro-randomized trials | C20: https://pmc.ncbi.nlm.nih.gov/articles/PMC5820391/ | D20: https://doi.org/10.1016/j.cct.2015.07.003 | E20: Open full text / DOI landing | F20: Located - readable source | G20: PMC open full text located for micro-randomized trials paper. | H20: Klasnja et al. — Micro-randomized trials pdf DOI readable source | I20: https://www.google.com/search?q=Klasnja+et+al.+%E2%80%94+Micro-randomized+trials+pdf+DOI+readable+source | J20: 2026-08-13 | K20: Located (not charted) | L20: methods | M20: methods | N20: A | O20: METHOD | P20: methods | Q20: research methods | R20: causal | S20: low | T20: MRT estimates proximal causal effects and time-varying moderation. | U20: [to chart] | V20: [to chart] | W20: [to chart] | X20: partial | Y20: no | Z20: Best for high-frequency digital prompts/JITAI. | AA20: Rigor for the digital channel. | AC20: Digital Capture Architecture | AE20: Methods / reporting standards | AF20: 36 months | AG20: 2026-08-13 | AH20: 2029-08-13 | AI20: Current - re-search on schedule
A21: CORE-20 | B21: Collins — Multiphase Optimization Strategy (MOST) | C21: https://methodology.psu.edu/wp-content/uploads/2020/05/Collins-2018-MOST-Overview.pdf | D21: https://www.springer.com/gp/book/9783319722054 | E21: Open PDF / book landing | F21: Located - readable source | G21: Readable MOST overview located; verify if matrix should reference book vs overview during charting. | H21: Collins — Multiphase Optimization Strategy (MOST) pdf DOI readable source | I21: https://www.google.com/search?q=Collins+%E2%80%94+Multiphase+Optimization+Strategy+%28MOST%29+pdf+DOI+readable+source | J21: 2026-08-13 | K21: Located (not charted) | L21: methods | M21: methods | N21: A | O21: METHOD | P21: methods | Q21: research methods | R21: causal | S21: low | T21: Factorial screening separates intervention-component effects. | U21: [to chart] | V21: [to chart] | W21: [to chart] | X21: partial | Y21: no | Z21: Channel attribution once components defined. | AA21: Avoid confounding the whole ecology. | AC21: Intervention Component Library | AD21: OC-3 | AE21: Methods / reporting standards | AF21: 36 months | AG21: 2026-08-13 | AH21: 2029-08-13 | AI21: Current - re-search on schedule
A22: A1-01 | B22: Hui — The Question Concerning Technology in China | C22: https://ia800505.us.archive.org/20/items/cyclonopedia-negarestani-reza/The_Question_Concerning_Technology_in_China--_Yuk_Hui.pdf | D22: https://brill.com/previewpdf/view/journals/dias/4/3/article-p316_316.xml | E22: PDF found / copyright status should be reviewed before relying on full-text copy | F22: Readable source found - verify rights/edition | G22: Use legally obtained copy if possible. Existing design memo relies more centrally on Hui 2024, which is open access. | H22: Hui — The Question Concerning Technology in China pdf DOI readable source | I22: https://www.google.com/search?q=Hui+%E2%80%94+The+Question+Concerning+Technology+in+China+pdf+DOI+readable+source | J22: 2026-08-13 | K22: Pending | L22: 1 | M22: WS-K | N22: A | O22: TELOS | P22: philosophical | Q22: philosophy of tech | R22: conceptual | S22: high | T22: Technology is not anthropologically universal; cosmotechnics binds cosmic + moral + technical. | U22: [to chart] | V22: [to chart] | W22: [to chart] | X22: partial | Y22: yes | Z22: Governing telos (layer 2.13); the plan's horizon. | AA22: Sets the whole cosmotechnic criterion. | AB22: CF-10 | AC22: Cosmotechnic Audit Card | AD22: OC-7 | AE22: Philosophical / historical / theoretical | AF22: 60 months | AG22: 2026-08-13 | AH22: 2031-08-13 | AI22: Current - re-search on schedule
A23: A1-02 | B23: Hui — Cosmotechnics as Cosmopolitics | C23: https://www.e-flux.com/journal/86/161887/cosmotechnics-as-cosmopolitics/ | D23: https://digitalmilieu.net/1248/cosmotechnics-as-cosmopolitics/ | E23: Open HTML | F23: Located - readable source | G23: Priority B pass: e-flux full text and author page located. | H23: Hui — Cosmotechnics as Cosmopolitics pdf DOI readable source | I23: https://www.google.com/search?q=Hui+%E2%80%94+Cosmotechnics+as+Cosmopolitics+pdf+DOI+readable+source | J23: 2026-08-13 | K23: Located (not charted) | L23: 10 | M23: WS-K | N23: B | O23: TELOS/CRITIQUE | P23: philosophical | Q23: philosophy of tech | R23: conceptual | S23: high | T23: Resists unilateral globalization of one technical worldview; technodiversity. | U23: [to chart] | V23: [to chart] | W23: [to chart] | X23: no | Y23: yes | Z23: Support personal technodiversity. | AA23: Refuse one productivity ontology. | AB23: CF-8 | AC23: Technodiversity & Cultural Fit Sheet | AD23: OC-11 | AE23: Philosophical / historical / theoretical | AF23: 60 months | AG23: 2026-08-13 | AH23: 2031-08-13 | AI23: Current - re-search on schedule
A24: A1-03 | B24: Hui — Art and Cosmotechnics | C24: https://www.e-flux.com/books/327526/art-and-cosmotechnics | D24: https://www.upress.umn.edu/9781517909543/art-and-cosmotechnics/ | E24: Publisher/e-flux landing | F24: Located - landing source | G24: Priority B pass: publisher and e-flux book landing found; full text may require purchase/library. | H24: Hui — Art and Cosmotechnics pdf DOI readable source | I24: https://www.google.com/search?q=Hui+%E2%80%94+Art+and+Cosmotechnics+pdf+DOI+readable+source | J24: 2026-08-13 | K24: Located (not charted) | L24: 1 | M24: WS-K | N24: B | O24: TELOS | P24: philosophical | Q24: philosophy of tech | R24: conceptual | S24: medium | T24: Art/landscape/symbol as resources to rethink technology beyond instrumentality. | U24: [to chart] | V24: [to chart] | W24: [to chart] | X24: no | Y24: yes | Z24: Justify ritual/symbolic/registration elements. | AA24: Aesthetic-symbolic relation as technical. | AB24: CF-7 | AC24: Ritual Transition Cards | AE24: Philosophical / historical / theoretical | AF24: 60 months | AG24: 2026-08-13 | AH24: 2031-08-13 | AI24: Current - re-search on schedule
A25: A1-04 | B25: Hui & Lemmens (eds.) — Cosmotechnics (Anthropocene) | C25: https://api.pageplace.de/preview/DT0400.9781000396324_A40918824/preview-9781000396324_A40918824.pdf | D25: https://www.routledge.com/Cosmotechnics-For-a-Renewed-Concept-of-Technology-in-the-Anthropocene/Hui-Lemmens/p/book/9780367769376 | E25: Preview PDF / publisher landing | F25: Located - preview source | G25: Priority B pass: preview/source landing found; full book likely library/purchase. | H25: Hui & Lemmens (eds.) — Cosmotechnics (Anthropocene) pdf DOI readable source | I25: https://www.google.com/search?q=Hui+%26+Lemmens+%28eds.%29+%E2%80%94+Cosmotechnics+%28Anthropocene%29+pdf+DOI+readable+source | J25: 2026-08-13 | K25: Located (not charted) | L25: 1 | M25: WS-K | N25: B | O25: TELOS | P25: review | Q25: philosophy of tech | R25: conceptual | S25: medium | T25: Technodiversity, pluralism, ecological stakes of technical practice. | U25: [to chart] | V25: [to chart] | W25: [to chart] | X25: no | Y25: yes | Z25: Pluralism at the scale of practice. | AA25: Ecological stakes of tools. | AB25: CF-8 | AC25: Cosmotechnic Audit Card | AE25: Empirical / applied research | AF25: 24 months | AG25: 2026-08-13 | AH25: 2028-08-13 | AI25: Current - re-search on schedule
A26: A1-05 | B26: Simondon — On the Mode of Existence of Technical Objects | C26: https://archive.org/details/onmodeofexistenc0000simo | D26: https://www.upress.umn.edu/9781937561031/on-the-mode-of-existence-of-technical-objects/ | E26: Archive lending / publisher landing | F26: Located - restricted readable | G26: Archive/publisher page located; use legal borrowed/purchased text for charting. | H26: Simondon — On the Mode of Existence of Technical Objects pdf DOI readable source | I26: https://www.google.com/search?q=Simondon+%E2%80%94+On+the+Mode+of+Existence+of+Technical+Objects+pdf+DOI+readable+source | J26: 2026-08-13 | K26: Located (not charted) | L26: 1 | M26: WS-K | N26: A | O26: TELOS/MECHANISM/DESIGN | P26: philosophical | Q26: philosophy of tech | R26: conceptual | S26: high | T26: Technical objects are evolving relational beings, not inert tools. | U26: [to chart] | V26: [to chart] | W26: [to chart] | X26: no | Y26: yes | Z26: Technical-object maturity; tool subordination. | AA26: Judge whether a tool integrates or alienates. | AB26: CF-5 | AC26: Cosmotechnic Audit Card | AE26: Philosophical / historical / theoretical | AF26: 60 months | AG26: 2026-08-13 | AH26: 2031-08-13 | AI26: Current - located, access/fit caveat
A27: A1-06 | B27: Simondon — Individuation (Form and Information) | C27: https://archive.org/details/individuationinl0000simo | D27: https://www.upress.umn.edu/9781937561048/individuation-in-light-of-notions-of-form-and-information/ | E27: Archive lending / publisher landing | F27: Located - restricted readable | G27: Archive/publisher page located for Simondon Individuation. | H27: Simondon — Individuation (Form and Information) pdf DOI readable source | I27: https://www.google.com/search?q=Simondon+%E2%80%94+Individuation+%28Form+and+Information%29+pdf+DOI+readable+source | J27: 2026-08-13 | K27: Located (not charted) | L27: 1 | M27: WS-K | N27: A | O27: TELOS/MECHANISM | P27: philosophical | Q27: philosophy of tech | R27: conceptual | S27: medium | T27: The person is an individuating system shaped through relations, not a fixed agent. | U27: [to chart] | V27: [to chart] | W27: [to chart] | X27: no | Y27: yes | Z27: Avoid rigid identity protocols. | AA27: Support becoming-through-practice. | AB27: CF-8 | AC27: Monstare Protocol vNext | AE27: Philosophical / historical / theoretical | AF27: 60 months | AG27: 2026-08-13 | AH27: 2031-08-13 | AI27: Current - located, access/fit caveat
A28: A1-07 | B28: Stiegler — Technics and Time v1 (Fault of Epimetheus) | C28: https://monoskop.org/images/6/6c/Stiegler_Bernard_Technics_and_Time_1_The_Fault_of_Epimetheus.pdf | D28: https://www.sup.org/books/title/?id=2213 | E28: Open PDF / publisher landing | F28: Located - readable source | G28: Readable PDF located; verify legality/preferred access during charting. | H28: Stiegler — Technics and Time v1 (Fault of Epimetheus) pdf DOI readable source | I28: https://www.google.com/search?q=Stiegler+%E2%80%94+Technics+and+Time+v1+%28Fault+of+Epimetheus%29+pdf+DOI+readable+source | J28: 2026-08-13 | K28: Located (not charted) | L28: 1 | M28: WS-K | N28: A | O28: TELOS/WARNING | P28: philosophical | Q28: philosophy of tech | R28: conceptual | S28: high | T28: Technics constitutes memory/inheritance; external memory is pharmakon (remedy+poison). | U28: [to chart] | V28: [to chart] | W28: [to chart] | X28: partial | Y28: yes | Z28: Frame external memory/AI as pharmacological. | AA28: Offloading has a poison dose. | AB28: CF-3 | AC28: AI Assistant Use Rules | AD28: OC-13 | AE28: Philosophical / historical / theoretical | AF28: 60 months | AG28: 2026-08-13 | AH28: 2031-08-13 | AI28: Current - re-search on schedule
A29: A1-08 | B29: Feenberg — Questioning Technology | C29: https://www.sfu.ca/~andrewf/Feenberg_Questioning_Technology.pdf | D29: https://www.routledge.com/Questioning-Technology/Feenberg/p/book/9780415197552 | E29: Open PDF / publisher landing | F29: Located - readable source | G29: Readable PDF located for Questioning Technology. | H29: Feenberg — Questioning Technology pdf DOI readable source | I29: https://www.google.com/search?q=Feenberg+%E2%80%94+Questioning+Technology+pdf+DOI+readable+source | J29: 2026-08-13 | K29: Located (not charted) | L29: 1 | M29: WS-K | N29: A | O29: CRITIQUE/DESIGN/TELOS | P29: philosophical | Q29: critical theory of tech | R29: conceptual | S29: high | T29: Technology is not neutral and can be democratized. | U29: [to chart] | V29: [to chart] | W29: [to chart] | X29: no | Y29: yes | Z29: User authorship beyond interface choice. | AA29: Design politics as moral stake. | AB29: CF-10 | AC29: Cosmotechnic Audit Card | AE29: Philosophical / historical / theoretical | AF29: 60 months | AG29: 2026-08-13 | AH29: 2031-08-13 | AI29: Current - re-search on schedule
A30: A1-09 | B30: Ihde — Technology and the Lifeworld | C30: https://archive.org/details/technologylifewo0000ihde | D30: https://iupress.org/9780253205605/technology-and-the-lifeworld/ | E30: Archive lending / publisher landing | F30: Located - restricted readable | G30: Archive lending and publisher page located. | H30: Ihde — Technology and the Lifeworld pdf DOI readable source | I30: https://www.google.com/search?q=Ihde+%E2%80%94+Technology+and+the+Lifeworld+pdf+DOI+readable+source | J30: 2026-08-13 | K30: Located (not charted) | L30: 1 | M30: WS-K | N30: A | O30: TELOS/MECHANISM | P30: philosophical | Q30: postphenomenology | R30: conceptual | S30: medium | T30: Technologies mediate perception and action (reveal/conceal/amplify/reduce). | U30: [to chart] | V30: [to chart] | W30: [to chart] | X30: no | Y30: yes | Z30: Ask what a tool reveals and hides. | AA30: Mediation as design question. | AB30: CF-5 | AC30: Cosmotechnic Audit Card | AE30: Philosophical / historical / theoretical | AF30: 60 months | AG30: 2026-08-13 | AH30: 2031-08-13 | AI30: Current - located, access/fit caveat
A31: A1-10 | B31: Verbeek — What Things Do | C31: https://archive.org/details/whatthingsdophil0000verb | D31: https://www.psupress.org/books/titles/0-271-02540-9.html | E31: Archive lending / publisher landing | F31: Located - restricted readable | G31: Archive lending and publisher page located. | H31: Verbeek — What Things Do pdf DOI readable source | I31: https://www.google.com/search?q=Verbeek+%E2%80%94+What+Things+Do+pdf+DOI+readable+source | J31: 2026-08-13 | K31: Located (not charted) | L31: 1 | M31: WS-L | N31: A | O31: DESIGN/TELOS/WARNING | P31: philosophical | Q31: postphenomenology | R31: conceptual | S31: high | T31: Technologies are moral mediators of action. | U31: [to chart] | V31: [to chart] | W31: [to chart] | X31: no | Y31: yes | Z31: Vocabulary for technological mediation of moral action. | AA31: Design as ethics-in-practice. | AB31: CF-4 | AC31: Cosmotechnic Audit Card | AE31: Philosophical / historical / theoretical | AF31: 60 months | AG31: 2026-08-13 | AH31: 2031-08-13 | AI31: Current - located, access/fit caveat
A32: A1-11 | B32: Winner — The Whale and the Reactor | C32: https://ratical.org/ratville/AoS/WhaleAndReactor.pdf | D32: https://press.uchicago.edu/ucp/books/book/chicago/W/bo5958056.html | E32: Open PDF / publisher landing | F32: Located - readable source | G32: Priority B pass: readable PDF located alongside Chicago publisher page. | H32: Winner — The Whale and the Reactor pdf DOI readable source | I32: https://www.google.com/search?q=Winner+%E2%80%94+The+Whale+and+the+Reactor+pdf+DOI+readable+source | J32: 2026-08-13 | K32: Located (not charted) | L32: 1 | M32: WS-L | N32: B | O32: WARNING/CRITIQUE | P32: philosophical | Q32: politics of tech | R32: conceptual | S32: medium | T32: Artifacts can embody politics. | U32: [to chart] | V32: [to chart] | W32: [to chart] | X32: no | Y32: yes | Z32: Ask whether an artifact enforces a moral/political order. | AA32: Artifacts are not neutral. | AB32: CF-10 | AC32: Design Veto Catalogue | AE32: Philosophical / historical / theoretical | AF32: 60 months | AG32: 2026-08-13 | AH32: 2031-08-13 | AI32: Current - re-search on schedule
A33: A1-12 | B33: Latour — Where Are the Missing Masses? | C33: https://www.bruno-latour.fr/node/258.html | D33: https://www.sfu.ca/~andrewf/Latour_MissingMasses.pdf | E33: Open HTML / PDF | F33: Located - readable source | G33: Priority B pass: author/official page and PDF located. | H33: Latour — Where Are the Missing Masses? pdf DOI readable source | I33: https://www.google.com/search?q=Latour+%E2%80%94+Where+Are+the+Missing+Masses%3F+pdf+DOI+readable+source | J33: 2026-08-13 | K33: Located (not charted) | L33: 1 | M33: WS-L | N33: B | O33: MECHANISM/DESIGN | P33: theoretical | Q33: STS | R33: conceptual | S33: medium | T33: Artifacts delegate, prescribe, and shape conduct. | U33: [to chart] | V33: [to chart] | W33: [to chart] | X33: no | Y33: partial | Z33: Task design as delegated morality. | AA33: Prescription is embedded in tools. | AB33: CF-4 | AC33: Monstare Protocol vNext | AE33: General supporting source | AF33: 36 months | AG33: 2026-08-13 | AH33: 2029-08-13 | AI33: Current - re-search on schedule
A34: A1-13 | B34: Borgmann — Technology and the Character of Contemporary Life | C34: https://archive.org/details/technologycharac0000borg | D34: https://press.uchicago.edu/ucp/books/book/chicago/T/bo3632495.html | E34: Archive lending / publisher landing | F34: Located - restricted readable | G34: Priority B pass: archive loan and publisher page located. | H34: Borgmann — Technology and the Character of Contemporary Life pdf DOI readable source | I34: https://www.google.com/search?q=Borgmann+%E2%80%94+Technology+and+the+Character+of+Contemporary+Life+pdf+DOI+readable+source | J34: 2026-08-13 | K34: Located (not charted) | L34: 1 | M34: WS-L | N34: B | O34: WARNING/TELOS | P34: philosophical | Q34: philosophy of tech | R34: conceptual | S34: medium | T34: Device paradigm hides focal practices behind commodities. | U34: [to chart] | V34: [to chart] | W34: [to chart] | X34: no | Y34: yes | Z34: Protect practice from convenience extraction. | AA34: Convenience can erase focal practice. | AB34: CF-5 | AC34: Anti-Extraction Audit | AE34: Philosophical / historical / theoretical | AF34: 60 months | AG34: 2026-08-13 | AH34: 2031-08-13 | AI34: Current - located, access/fit caveat
A35: A1-14 | B35: Mitcham — Thinking Through Technology | C35: https://archive.org/details/thinkingthrought0000mitc | D35: https://press.uchicago.edu/ucp/books/book/chicago/T/bo3625112.html | E35: Archive lending / publisher landing | F35: Located - restricted readable | G35: Priority B pass: archive loan and publisher page located. | H35: Mitcham — Thinking Through Technology pdf DOI readable source | I35: https://www.google.com/search?q=Mitcham+%E2%80%94+Thinking+Through+Technology+pdf+DOI+readable+source | J35: 2026-08-13 | K35: Located (not charted) | L35: 1 | M35: WS-K | N35: B | O35: TELOS/REVIEW | P35: review | Q35: philosophy of tech | R35: conceptual | S35: low | T35: Map of engineering vs humanities approaches to technology. | U35: [to chart] | V35: [to chart] | W35: [to chart] | X35: no | Y35: partial | Z35: Orient without overcommitting to one school. | AA35: Breadth over dogma. | AC35: Master Research Index | AE35: Empirical / applied research | AF35: 24 months | AG35: 2026-08-13 | AH35: 2028-08-13 | AI35: Current - located, access/fit caveat
A36: A1-15 | B36: Heidegger — The Question Concerning Technology | C36: https://monoskop.org/images/6/67/Heidegger_Martin_1962_1977_The_Question_Concerning_Technology.pdf | D36: https://monoskop.org/images/4/44/Heidegger_Martin_The_Question_Concerning_Technology_and_Other_Essays.pdf | E36: Open PDF copies / verify legal course-use copy | F36: Located - readable source | G36: Essay PDF and collected-volume PDF located; use legal/approved copy for charting. | H36: Heidegger — The Question Concerning Technology pdf DOI readable source | I36: https://www.google.com/search?q=Heidegger+%E2%80%94+The+Question+Concerning+Technology+pdf+DOI+readable+source | J36: 2026-08-13 | K36: Pending | L36: 1 | M36: WS-K | N36: C | O36: TELOS/CRITIQUE | P36: philosophical | Q36: philosophy of tech | R36: conceptual | S36: medium | T36: Enframing; technology as a mode of revealing. | U36: [to chart] | V36: [to chart] | W36: [to chart] | X36: no | Y36: yes | Z36: Pressure source, not governing authority (Hui responds to it). | AA36: Origin-point for the universality problem. | AB36: CF-8 | AC36: Cosmotechnic Audit Card | AE36: Philosophical / historical / theoretical | AF36: 60 months | AG36: 2026-08-13 | AH36: 2031-08-13 | AI36: Current - re-search on schedule
A37: A1-16 | B37: Mumford — Technics and Civilization | C37: https://archive.org/details/technicsciviliza0000lewi | D37: https://openlibrary.org/books/OL13718419M/Technics_and_civilization. | E37: Archive lending / Open Library landing | F37: Located - restricted readable | G37: Controlled digital lending and catalog path located for Technics and Civilization. | H37: Mumford — Technics and Civilization pdf DOI readable source | I37: https://www.google.com/search?q=Mumford+%E2%80%94+Technics+and+Civilization+pdf+DOI+readable+source | J37: 2026-08-13 | K37: Pending | L37: 1 | M37: WS-K | N37: C | O37: TELOS/CONTEXT | P37: theoretical | Q37: history of tech | R37: conceptual | S37: low | T37: Long history of technics and social form. | U37: [to chart] | V37: [to chart] | W37: [to chart] | X37: no | Y37: partial | Z37: Context only. | AA37: Historical breadth. | AC37: Master Research Index | AE37: General supporting source | AF37: 36 months | AG37: 2026-08-13 | AH37: 2029-08-13 | AI37: Current - located, access/fit caveat
A38: A1-17 | B38: Ellul — The Technological Society | C38: https://archive.org/details/technologicalsoc0000ellu | D38: https://archive.org/details/JacquesEllulTheTechnologicalSociety | E38: Archive lending / alternate archive scan | F38: Located - restricted readable | G38: Archive access path located; use legal borrowed/library copy for full charting. | H38: Ellul — The Technological Society pdf DOI readable source | I38: https://www.google.com/search?q=Ellul+%E2%80%94+The+Technological+Society+pdf+DOI+readable+source | J38: 2026-08-13 | K38: Pending | L38: 1 | M38: WS-K | N38: C | O38: WARNING | P38: theoretical | Q38: philosophy of tech | R38: conceptual | S38: medium | T38: Technique as autonomous, self-augmenting order. | U38: [to chart] | V38: [to chart] | W38: [to chart] | X38: no | Y38: yes | Z38: Warning about technical autonomy. | AA38: Technique can govern the human. | AB38: CF-4 | AC38: Design Veto Catalogue | AE38: Philosophical / historical / theoretical | AF38: 60 months | AG38: 2026-08-13 | AH38: 2031-08-13 | AI38: Current - located, access/fit caveat
A39: A1-18 | B39: Haraway — A Cyborg Manifesto | C39: https://www.sfu.ca/~decaste/OISE/page2/files/HarawayCyborg.pdf | D39: https://archive.org/details/anarchy_Cyborg_Manifesto_Harroway | E39: Open PDF / archive landing | F39: Located - readable source | G39: Readable PDF and archive landing located; verify preferred edition during charting. | H39: Haraway — A Cyborg Manifesto pdf DOI readable source | I39: https://www.google.com/search?q=Haraway+%E2%80%94+A+Cyborg+Manifesto+pdf+DOI+readable+source | J39: 2026-08-13 | K39: Pending | L39: 1 | M39: WS-L | N39: C | O39: CRITIQUE | P39: theoretical | Q39: STS/feminist | R39: conceptual | S39: low | T39: Hybrid human-machine boundaries; refusal of purity. | U39: [to chart] | V39: [to chart] | W39: [to chart] | X39: no | Y39: partial | Z39: Contextual reframing. | AA39: Boundary plurality. | AC39: Technodiversity & Cultural Fit Sheet | AE39: General supporting source | AF39: 36 months | AG39: 2026-08-13 | AH39: 2029-08-13 | AI39: Current - re-search on schedule
A40: A1-19 | B40: Verbeek — Moralizing Technology | C40: https://archive.org/details/moralizingtechno0000verb | D40: https://press.uchicago.edu/ucp/books/book/chicago/M/bo11309162.html | E40: Archive lending / publisher landing | F40: Located - restricted readable | G40: Archive lending and University of Chicago Press landing located. | H40: Verbeek — Moralizing Technology pdf DOI readable source | I40: https://www.google.com/search?q=Verbeek+%E2%80%94+Moralizing+Technology+pdf+DOI+readable+source | J40: 2026-08-13 | K40: Pending | L40: 1 | M40: WS-L | N40: C | O40: DESIGN/TELOS | P40: philosophical | Q40: postphenomenology | R40: conceptual | S40: medium | T40: Designers materialize morality; ethics of things. | U40: [to chart] | V40: [to chart] | W40: [to chart] | X40: no | Y40: yes | Z40: Deliberate moral mediation in design. | AA40: Morality can be built in. | AB40: CF-4 | AC40: Cosmotechnic Audit Card | AE40: Philosophical / historical / theoretical | AF40: 60 months | AG40: 2026-08-13 | AH40: 2031-08-13 | AI40: Current - located, access/fit caveat
A41: A2-01 | B41: Li, Dey & Forlizzi — Stage-Based Model of Personal Informatics | C41: https://www.ianli.com/publications/2010-ianli-chi-stage-based-model.pdf | D41: https://ianli.owlstown.net/publications/17-a-stage-based-model-of-personal-informatics-systems | E41: Open PDF | F41: Readable source found | G41: CHI 2010 paper; DOI surfaced in search result as 10.1145/1753326.1753409. | H41: Li, Dey & Forlizzi — Stage-Based Model of Personal Informatics pdf DOI readable source | I41: https://www.google.com/search?q=Li%2C+Dey+%26+Forlizzi+%E2%80%94+Stage-Based+Model+of+Personal+Informatics+pdf+DOI+readable+source | J41: 2026-08-13 | K41: Pending | L41: 2 | M41: WS-F | N41: A | O41: MECHANISM/DESIGN/METHOD | P41: theoretical | Q41: HCI/PI | R41: conceptual | S41: high | T41: PI stages: preparation, collection, integration, reflection, action. | U41: [to chart] | V41: [to chart] | W41: [to chart] | X41: partial | Y41: yes | Z41: Design capture workflow; prevent data hoarding without reflection. | AA41: Capture must serve reflection, not accumulation. | AB41: CF-2 | AC41: Digital Capture Architecture | AE41: Empirical / applied research | AF41: 24 months | AG41: 2026-08-13 | AH41: 2028-08-13 | AI41: Current - re-search on schedule
A42: A2-02 | B42: Lupton — The Quantified Self | C42: https://bpb-us-e2.wpmucdn.com/sites.middlebury.edu/dist/b/5028/files/2020/02/lupton-quantified-self-ch1.pdf | D42: https://www.perlego.com/book/1536278/the-quantified-self-pdf | E42: Chapter PDF / book access options | F42: Partial readable source found | G42: Full book is a copyrighted monograph; use chapter extracts or legal library/e-book access for full charting. | H42: Lupton — The Quantified Self pdf DOI readable source | I42: https://www.google.com/search?q=Lupton+%E2%80%94+The+Quantified+Self+pdf+DOI+readable+source | J42: 2026-08-13 | K42: Pending | L42: 2 | M42: WS-F | N42: A | O42: CRITIQUE/WARNING | P42: critique | Q42: sociology | R42: conceptual | S42: high | T42: Self-tracking datafies selfhood; risks neoliberal self-management. | U42: [to chart] | V42: [to chart] | W42: [to chart] | X42: no | Y42: yes | Z42: Name metric-capture and self-discipline risks. | AA42: Numbers can displace self-knowledge. | AB42: CF-2 | AC42: Anti-Extraction Audit | AD42: OC-10 | AE42: General supporting source | AF42: 36 months | AG42: 2026-08-13 | AH42: 2029-08-13 | AI42: Current - re-search on schedule
A43: A2-03 | B43: Neff & Nafus — Self-Tracking | C43: https://archive.org/details/selftracking0000neff | D43: https://mitpress.mit.edu/9780262529129/self-tracking/ | E43: Archive lending / publisher landing | F43: Located - restricted readable | G43: Archive lending and MIT Press landing located. | H43: Neff & Nafus — Self-Tracking pdf DOI readable source | I43: https://www.google.com/search?q=Neff+%26+Nafus+%E2%80%94+Self-Tracking+pdf+DOI+readable+source | J43: 2026-08-13 | K43: Located (not charted) | L43: 2 | M43: WS-F | N43: A | O43: CRITIQUE/DESIGN | P43: critique | Q43: STS | R43: conceptual | S43: medium | T43: Maps self-tracking practices and their social implications. | U43: [to chart] | V43: [to chart] | W43: [to chart] | X43: no | Y43: partial | Z43: Distinguish self-knowledge, self-surveillance, experiment. | AA43: Tracking is a cultural practice. | AB43: CF-2 | AC43: Anti-Extraction Audit | AE43: General supporting source | AF43: 36 months | AG43: 2026-08-13 | AH43: 2029-08-13 | AI43: Current - located, access/fit caveat
A44: A2-04 | B44: Rapp, Cena & Marcengo — QS/PI special issue editorial | C44: https://link.springer.com/content/pdf/10.1007/s00779-017-1093-x.pdf | D44: https://link.springer.com/article/10.1007/s00779-017-1093-x | E44: Open PDF / DOI landing | F44: Located - readable source | G44: Readable Springer PDF located for QS/PI special issue editorial. | H44: Rapp, Cena & Marcengo — QS/PI special issue editorial pdf DOI readable source | I44: https://www.google.com/search?q=Rapp%2C+Cena+%26+Marcengo+%E2%80%94+QS%2FPI+special+issue+editorial+pdf+DOI+readable+source | J44: 2026-08-13 | K44: Located (not charted) | L44: 2 | M44: WS-H | N44: A | O44: REVIEW/DESIGN | P44: review | Q44: HCI/PI | R44: conceptual | S44: medium | T44: PI aims to make personal data meaningful in situated daily life. | U44: [to chart] | V44: [to chart] | W44: [to chart] | X44: partial | Y44: partial | Z44: Situated usefulness over total capture. | AA44: Meaning in context, not raw data. | AB44: CF-2 | AC44: Digital Capture Architecture | AE44: Empirical / applied research | AF44: 24 months | AG44: 2026-08-13 | AH44: 2028-08-13 | AI44: Current - re-search on schedule
A45: A2-05 | B45: Grinberg — Ethnography of an Interface | C45: https://digitalassets.lib.berkeley.edu/anthpubs/ucb/text/kas061_003-006.pdf | D45: https://escholarship.org/uc/item/0h1008ws | E45: Open PDF / repository landing | F45: Located - readable source | G45: Readable repository PDF located; verify exact ethnography/interface match during charting. | H45: Grinberg — Ethnography of an Interface pdf DOI readable source | I45: https://www.google.com/search?q=Grinberg+%E2%80%94+Ethnography+of+an+Interface+pdf+DOI+readable+source | J45: 2026-08-13 | K45: Located (not charted) | L45: 2 | M45: WS-F | N45: A | O45: CRITIQUE/CONTEXT | P45: empirical | Q45: anthropology | R45: correlational | S45: medium | T45: QS as culture of personal data and digital connection. | U45: [to chart] | V45: [to chart] | W45: [to chart] | X45: no | Y45: partial | Z45: See tracking as social/technical, not neutral. | AA45: Interfaces shape self-relation. | AB45: CF-2 | AC45: Anti-Extraction Audit | AE45: Empirical / applied research | AF45: 24 months | AG45: 2026-08-13 | AH45: 2028-08-13 | AI45: Current - re-search on schedule
A46: A2-06 | B46: Sharon — Self-Tracking for Health and the QS | C46: https://www.academia.edu/9958013/Self_Tracking_for_Health_and_the_Quantified_Self_Re_articulating_Autonomy_Solidarity_and_Authenticity_in_an_Age_of_Personalized_Healthcare | D46: https://doi.org/10.1007/s10676-016-9405-0 | E46: Academia landing / DOI landing | F46: Located - gated or account source | G46: Source located; full text may require institution/account or publisher access. | H46: Sharon — Self-Tracking for Health and the QS pdf DOI readable source | I46: https://www.google.com/search?q=Sharon+%E2%80%94+Self-Tracking+for+Health+and+the+QS+pdf+DOI+readable+source | J46: 2026-08-13 | K46: Located (not charted) | L46: 2 | M46: WS-F | N46: A | O46: CRITIQUE/ETHICS | P46: critique | Q46: ethics/STS | R46: conceptual | S46: medium | T46: Does self-tracking empower or discipline the self? | U46: [to chart] | V46: [to chart] | W46: [to chart] | X46: no | Y46: yes | Z46: Ethical boundary for state/productivity tracking. | AA46: Empowerment vs discipline. | AB46: CF-2 | AC46: Cosmotechnic Audit Card | AE46: General supporting source | AF46: 36 months | AG46: 2026-08-13 | AH46: 2029-08-13 | AI46: Current - re-search on schedule
A47: A2-07 | B47: Whittaker — critiques of QS/personal informatics | C47: https://external.dandelon.com/download/attachments/dandelon/ids/CH001C626918F45F6881DC1258006003EC0A8.pdf | D47: https://www.politybooks.com/bookdetail?book_slug=the-quantified-self--9781509500611 | E47: Preview PDF / publisher landing | F47: Located - partial source | G47: Priority B pass: core critique source located around QS critique; check whether row label needs Whittaker→Lupton correction. | H47: Whittaker — critiques of QS/personal informatics pdf DOI readable source | I47: https://www.google.com/search?q=Whittaker+%E2%80%94+critiques+of+QS%2Fpersonal+informatics+pdf+DOI+readable+source | J47: 2026-08-13 | K47: Located (not charted) | L47: 2 | M47: WS-F | N47: B | O47: CRITIQUE/DESIGN | P47: critique | Q47: HCI | R47: conceptual | S47: medium | T47: QS can be over-analytic, rationalistic, and authoritative. | U47: [to chart] | V47: [to chart] | W47: [to chart] | X47: no | Y47: partial | Z47: Avoid over-analytic capture that fails lived practice. | AA47: Analysis can overrun experience. | AB47: CF-2 | AC47: Phenomenological Registration Sheet | AE47: Empirical / applied research | AF47: 24 months | AG47: 2026-08-13 | AH47: 2028-08-13 | AI47: Current - re-search on schedule
A48: A2-08 | B48: Rapp & Tirassa — PI for sport and healthy behavior | C48: https://iris.unito.it/retrieve/handle/2318/1679773/447148/POST-PRINT.pdf | D48: https://doi.org/10.1145/3196829 | E48: Open postprint / DOI landing | F48: Located - readable source | G48: Priority B pass: open postprint located. | H48: Rapp & Tirassa — PI for sport and healthy behavior pdf DOI readable source | I48: https://www.google.com/search?q=Rapp+%26+Tirassa+%E2%80%94+PI+for+sport+and+healthy+behavior+pdf+DOI+readable+source | J48: 2026-08-13 | K48: Located (not charted) | L48: 2 | M48: WS-H | N48: B | O48: DESIGN/MECHANISM | P48: theoretical | Q48: HCI/PI | R48: conceptual | S48: low | T48: Translating PI into behavior change while watching limits. | U48: [to chart] | V48: [to chart] | W48: [to chart] | X48: partial | Y48: partial | Z48: Behavior-change translation. | AA48: Watch the limits. | AC48: Intervention Component Library | AE48: Empirical / applied research | AF48: 24 months | AG48: 2026-08-13 | AH48: 2028-08-13 | AI48: Current - re-search on schedule
A49: A2-09 | B49: Elsden et al. — making sense of personal data | C49: https://elsden.me/publications/ | D49: https://dl.acm.org/doi/10.1145/2858036.2858403 | E49: Author publications / DOI landing | F49: Located - landing source | G49: Priority B pass: author publication page and DOI located; needs exact full-text retrieval next. | H49: Elsden et al. — making sense of personal data pdf DOI readable source | I49: https://www.google.com/search?q=Elsden+et+al.+%E2%80%94+making+sense+of+personal+data+pdf+DOI+readable+source | J49: 2026-08-13 | K49: Located (not charted) | L49: 2 | M49: WS-F | N49: B | O49: DESIGN/CRITIQUE | P49: empirical | Q49: HCI | R49: correlational | S49: low | T49: Plural, experiential interpretations of personal data. | U49: [to chart] | V49: [to chart] | W49: [to chart] | X49: no | Y49: partial | Z49: Support plural data interpretation. | AA49: Data is interpreted, not given. | AB49: CF-2 | AC49: Phenomenological Registration Sheet | AE49: Empirical / applied research | AF49: 24 months | AG49: 2026-08-13 | AH49: 2028-08-13 | AI49: Current - re-search on schedule
A50: A2-10 | B50: Selke — Lifelogging | C50: https://link.springer.com/content/pdf/10.1007/978-3-658-10416-0.pdf | D50: https://link.springer.com/book/10.1007/978-3-658-10416-0 | E50: Open/Publisher PDF | F50: Located - readable source | G50: Priority B pass: Springer PDF located. | H50: Selke — Lifelogging pdf DOI readable source | I50: https://www.google.com/search?q=Selke+%E2%80%94+Lifelogging+pdf+DOI+readable+source | J50: 2026-08-13 | K50: Located (not charted) | L50: 2 | M50: WS-H | N50: B | O50: CRITIQUE/CONTEXT | P50: review | Q50: media studies | R50: conceptual | S50: low | T50: Surveillance and identity implications of total capture. | U50: [to chart] | V50: [to chart] | W50: [to chart] | X50: no | Y50: partial | Z50: Surveillance caution. | AA50: Total capture erodes selfhood. | AB50: CF-2 | AC50: Anti-Extraction Audit | AD50: OC-10 | AE50: Empirical / applied research | AF50: 24 months | AG50: 2026-08-13 | AH50: 2028-08-13 | AI50: Current - re-search on schedule
A51: A3-01 | B51: Limerick, Coyle & Moore — Experience of Agency in HCI (review) | C51: https://pmc.ncbi.nlm.nih.gov/articles/PMC4140386/ | D51: https://research.gold.ac.uk/id/eprint/11426/ | E51: Open full text / PMC | F51: Readable source found | G51: Frontiers in Human Neuroscience 2014, DOI 10.3389/fnhum.2014.00643. | H51: Limerick, Coyle & Moore — Experience of Agency in HCI (review) pdf DOI readable source | I51: https://www.google.com/search?q=Limerick%2C+Coyle+%26+Moore+%E2%80%94+Experience+of+Agency+in+HCI+%28review%29+pdf+DOI+readable+source | J51: 2026-08-13 | K51: Pending | L51: 3 | M51: WS-F | N51: A | O51: MECHANISM/MEASURE/ETHICS | P51: review | Q51: HCI | R51: conceptual | S51: high | T51: Sense of agency in HCI links control, feedback, assistance, ethics. | U51: [to chart] | V51: [to chart] | W51: [to chart] | X51: partial | Y51: yes | Z51: Agency-preservation questions for tools/AI/forms. | AA51: Agency is designable and measurable. | AB51: CF-4 | AC51: Agency & Autonomy Checklist | AE51: Empirical / applied research | AF51: 24 months | AG51: 2026-08-13 | AH51: 2028-08-13 | AI51: Current - re-search on schedule
A52: A3-02 | B52: Bennett, Metatla, Roudaut & Mekler — HCI Agency/Autonomy | C52: https://arxiv.org/pdf/2301.12490 | D52: https://arxiv.org/abs/2301.12490 | E52: Open arXiv PDF / accepted CHI version | F52: Readable source found | G52: Search results identify ACM DOI 10.1145/3544548.3580651. Note title-order ambiguity: matrix says agency/autonomy; arXiv page says autonomy/agency. | H52: Bennett, Metatla, Roudaut & Mekler — HCI Agency/Autonomy pdf DOI readable source | I52: https://www.google.com/search?q=Bennett%2C+Metatla%2C+Roudaut+%26+Mekler+%E2%80%94+HCI+Agency%2FAutonomy+pdf+DOI+readable+source | J52: 2026-08-13 | K52: Pending | L52: 3 | M52: WS-L | N52: A | O52: REVIEW/CRITIQUE/DESIGN | P52: review | Q52: HCI | R52: conceptual | S52: high | T52: 30 years of ambiguous autonomy/agency usage in HCI. | U52: [to chart] | V52: [to chart] | W52: [to chart] | X52: no | Y52: yes | Z52: Force explicit agency criteria; kill vague autonomy talk. | AA52: Autonomy must be operationalized. | AB52: CF-10 | AC52: Agency & Autonomy Checklist | AD52: OC-7 | AE52: Empirical / applied research | AF52: 24 months | AG52: 2026-08-13 | AH52: 2028-08-13 | AI52: Current - re-search on schedule
A53: A3-03 | B53: Schroeder et al. — Goal-Directed Self-Tracking | C53: https://dl.acm.org/doi/pdf/10.1145/3242587.3242643 | D53: https://doi.org/10.1145/3242587.3242643 | E53: ACM PDF / DOI landing | F53: Located - source landing | G53: ACM source located; access may require institution. | H53: Schroeder et al. — Goal-Directed Self-Tracking pdf DOI readable source | I53: https://www.google.com/search?q=Schroeder+et+al.+%E2%80%94+Goal-Directed+Self-Tracking+pdf+DOI+readable+source | J53: 2026-08-13 | K53: Located (not charted) | L53: 3 | M53: WS-H | N53: A | O53: DESIGN/METHOD | P53: empirical | Q53: HCI | R53: correlational | S53: medium | T53: Self-tracking tools fail when goals are unstated/unsupported. | U53: [to chart] | V53: [to chart] | W53: [to chart] | X53: partial | Y53: partial | Z53: Every tracking field must have a goal and use-case. | AA53: No capture without purpose. | AB53: CF-2 | AC53: Digital Capture Architecture | AE53: Empirical / applied research | AF53: 24 months | AG53: 2026-08-13 | AH53: 2028-08-13 | AI53: Current - located, access/fit caveat
A54: A3-04 | B54: Baumer & Silberman — When the Implication Is Not to Design | C54: https://wtf.tw/ref/baumer.pdf | D54: https://dl.acm.org/doi/10.1145/2470654.2466455 | E54: Open PDF / DOI landing | F54: Located - readable source | G54: Readable PDF located for non-design implication article. | H54: Baumer & Silberman — When the Implication Is Not to Design pdf DOI readable source | I54: https://www.google.com/search?q=Baumer+%26+Silberman+%E2%80%94+When+the+Implication+Is+Not+to+Design+pdf+DOI+readable+source | J54: 2026-08-13 | K54: Located (not charted) | L54: 3 | M54: WS-L | N54: A | O54: CRITIQUE/DESIGN VETO | P54: critique | Q54: HCI | R54: conceptual | S54: high | T54: Sometimes the right move is not to build technology. | U54: [to chart] | V54: [to chart] | W54: [to chart] | X54: no | Y54: yes | Z54: Formalize technology refusal. | AA54: Non-design as a valid outcome. | AB54: CF-4/CF-9 | AC54: Design Veto Catalogue | AD54: OC-10 | AE54: Empirical / applied research | AF54: 24 months | AG54: 2026-08-13 | AH54: 2028-08-13 | AI54: Current - re-search on schedule
A55: A3-05 | B55: Sengers, Boehner, David & Kaye — Reflective Design | C55: https://people.csail.mit.edu/rcm/papers/ReflectiveDesign_CHI2005.pdf | D55: https://dl.acm.org/doi/10.1145/1054972.1055012 | E55: Open PDF / DOI landing | F55: Located - readable source | G55: Readable PDF located for Reflective Design. | H55: Sengers, Boehner, David & Kaye — Reflective Design pdf DOI readable source | I55: https://www.google.com/search?q=Sengers%2C+Boehner%2C+David+%26+Kaye+%E2%80%94+Reflective+Design+pdf+DOI+readable+source | J55: 2026-08-13 | K55: Located (not charted) | L55: 3 | M55: WS-F | N55: A | O55: CRITIQUE/DESIGN | P55: theoretical | Q55: HCI | R55: conceptual | S55: medium | T55: Design to foster reflection rather than seamless optimization. | U55: [to chart] | V55: [to chart] | W55: [to chart] | X55: no | Y55: yes | Z55: Friction can be morally useful. | AA55: Reflection over seamlessness. | AB55: CF-5 | AC55: Phenomenological Registration Sheet | AE55: Empirical / applied research | AF55: 24 months | AG55: 2026-08-13 | AH55: 2028-08-13 | AI55: Current - re-search on schedule
A56: A3-06 | B56: Bardzell & Bardzell — Humanistic HCI | C56: https://www.morganclaypool.com/doi/pdf/10.2200/S00438ED1V01Y201207HCI015 | D56: https://doi.org/10.2200/S00438ED1V01Y201207HCI015 | E56: Publisher PDF / DOI landing | F56: Located - readable source | G56: Publisher PDF located; access may vary. | H56: Bardzell & Bardzell — Humanistic HCI pdf DOI readable source | I56: https://www.google.com/search?q=Bardzell+%26+Bardzell+%E2%80%94+Humanistic+HCI+pdf+DOI+readable+source | J56: 2026-08-13 | K56: Located (not charted) | L56: 3 | M56: WS-L | N56: A | O56: TELOS/CRITIQUE | P56: theoretical | Q56: HCI | R56: conceptual | S56: medium | T56: Connects HCI to meaning, value, interpretation. | U56: [to chart] | V56: [to chart] | W56: [to chart] | X56: no | Y56: yes | Z56: Keep HCI layer from becoming usability-only. | AA56: Meaning as a design criterion. | AB56: CF-1 | AC56: Cosmotechnic Audit Card | AE56: Empirical / applied research | AF56: 24 months | AG56: 2026-08-13 | AH56: 2028-08-13 | AI56: Current - re-search on schedule
A57: A3-07 | B57: Friedman & Kahn — Value Sensitive Design | C57: https://nissenbaum.tech.cornell.edu/papers/Value_Sensitive_Design.pdf | D57: https://link.springer.com/content/pdf/10.1007/978-94-007-7844-3_4.pdf | E57: Open PDF / chapter PDF | F57: Located - readable source | G57: VSD paper/chapter source located; row label should include Borning in final citation if using this source. | H57: Friedman & Kahn — Value Sensitive Design pdf DOI readable source | I57: https://www.google.com/search?q=Friedman+%26+Kahn+%E2%80%94+Value+Sensitive+Design+pdf+DOI+readable+source | J57: 2026-08-13 | K57: Pending | L57: 3 | M57: WS-L | N57: B | O57: METHOD/DESIGN | P57: methods | Q57: HCI | R57: conceptual | S57: medium | T57: Method for embedding values into technology design. | U57: [to chart] | V57: [to chart] | W57: [to chart] | X57: no | Y57: yes | Z57: Embed values into artifact design. | AA57: Values-by-design. | AB57: CF-10 | AC57: Design Veto Catalogue | AE57: Empirical / applied research | AF57: 24 months | AG57: 2026-08-13 | AH57: 2028-08-13 | AI57: Current - re-search on schedule
A58: A3-08 | B58: Light, Burgess & Duguay — The Walkthrough Method | C58: https://salford-repository.worktribe.com/preview/1493547/The20Walkthrough20Method20-20Final20Pre-print20version1.pdf | D58: https://doi.org/10.1177/1461444816675438 | E58: Open preprint / DOI landing | F58: Located - readable source | G58: Author preprint and DOI landing located. | H58: Light, Burgess & Duguay — The Walkthrough Method pdf DOI readable source | I58: https://www.google.com/search?q=Light%2C+Burgess+%26+Duguay+%E2%80%94+The+Walkthrough+Method+pdf+DOI+readable+source | J58: 2026-08-13 | K58: Pending | L58: 3 | M58: WS-H | N58: B | O58: METHOD/CRITIQUE | P58: methods | Q58: media/HCI | R58: conceptual | S58: low | T58: Analyze apps via expected use, vision, interface, governance. | U58: [to chart] | V58: [to chart] | W58: [to chart] | X58: no | Y58: partial | Z58: Audit tools before adopting them. | AA58: Interrogate the app's intended use. | AB58: CF-5 | AC58: Digital Capture Architecture | AE58: Empirical / applied research | AF58: 24 months | AG58: 2026-08-13 | AH58: 2028-08-13 | AI58: Current - re-search on schedule
A59: A3-09 | B59: Pierce — Undesigning Technology | D59: https://doi.org/10.1145/2207676.2208540 | E59: DOI landing / ACM access | F59: Located - source landing | G59: No clearly legal open PDF found in pass; ACM DOI path recorded. | H59: Pierce — Undesigning Technology pdf DOI readable source | I59: https://www.google.com/search?q=Pierce+%E2%80%94+Undesigning+Technology+pdf+DOI+readable+source | J59: 2026-08-13 | K59: Pending | L59: 3 | M59: WS-L | N59: B | O59: DESIGN VETO/CRITIQUE | P59: theoretical | Q59: HCI | R59: conceptual | S59: medium | T59: Removal, refusal, deactivation as positive design moves. | U59: [to chart] | V59: [to chart] | W59: [to chart] | X59: no | Y59: yes | Z59: Support undesign/reversibility. | AA59: Refusal is design. | AB59: CF-9 | AC59: Reversibility Check | AE59: Empirical / applied research | AF59: 24 months | AG59: 2026-08-13 | AH59: 2028-08-13 | AI59: Current - located, access/fit caveat
A60: A3-10 | B60: Rapp & Boldi — open issues in persuasive technologies | C60: https://iris.unito.it/retrieve/handle/2318/2014670/1377111/HCII24-ready-v50-final.pdf | D60: https://doi.org/10.1007/978-3-031-60428-7_8 | E60: Open author manuscript / DOI landing | F60: Located - readable source | G60: Author manuscript and DOI landing located. | H60: Rapp & Boldi — open issues in persuasive technologies pdf DOI readable source | I60: https://www.google.com/search?q=Rapp+%26+Boldi+%E2%80%94+open+issues+in+persuasive+technologies+pdf+DOI+readable+source | J60: 2026-08-13 | K60: Pending | L60: 3 | M60: WS-F | N60: B | O60: WARNING/CRITIQUE | P60: review | Q60: HCI | R60: conceptual | S60: medium | T60: Manipulation and agency harms in persuasion design. | U60: [to chart] | V60: [to chart] | W60: [to chart] | X60: no | Y60: yes | Z60: Detect manipulation/agency harm. | AA60: Persuasion can override agency. | AB60: CF-4 | AC60: Design Veto Catalogue | AE60: Empirical / applied research | AF60: 24 months | AG60: 2026-08-13 | AH60: 2028-08-13 | AI60: Current - re-search on schedule
A61: A4-01 | B61: Kaplan & Kaplan — The Experience of Nature | C61: https://archive.org/details/experienceofnatu0000kapl | D61: https://www.cambridge.org/core/books/experience-of-nature/A378A2C517FB18B356519D1E5025001C | E61: Archive lending / publisher landing | F61: Located - restricted readable | G61: Archive lending and Cambridge landing located. | H61: Kaplan & Kaplan — The Experience of Nature pdf DOI readable source | I61: https://www.google.com/search?q=Kaplan+%26+Kaplan+%E2%80%94+The+Experience+of+Nature+pdf+DOI+readable+source | J61: 2026-08-13 | K61: Located (not charted) | L61: 4 | M61: WS-E | N61: A | O61: TELOS/MECHANISM | P61: theoretical | Q61: environmental psych | R61: conceptual | S61: high | T61: Attention Restoration Theory; directed-attention fatigue and recovery. | U61: [to chart] | V61: [to chart] | W61: [to chart] | X61: yes | Y61: yes | Z61: Design recovery environments (the restoration half). | AA61: Recovery depends on relation to place. | AB61: CF-6 | AC61: Arousal/Flow/Task-Switching Layer | AE61: Empirical / applied research | AF61: 24 months | AG61: 2026-08-13 | AH61: 2028-08-13 | AI61: Current - located, access/fit caveat
A62: A4-02 | B62: Berman, Jonides & Kaplan — Cognitive Benefits of Nature | C62: https://www.umich.edu/~jlabpsyc/pdf/2008_2.pdf | D62: https://doi.org/10.1111/j.1467-9280.2008.02225.x | E62: Open PDF / DOI landing | F62: Located - readable source | G62: Readable PDF located for cognitive benefits of nature interaction. | H62: Berman, Jonides & Kaplan — Cognitive Benefits of Nature pdf DOI readable source | I62: https://www.google.com/search?q=Berman%2C+Jonides+%26+Kaplan+%E2%80%94+Cognitive+Benefits+of+Nature+pdf+DOI+readable+source | J62: 2026-08-13 | K62: Located (not charted) | L62: 4 | M62: WS-E | N62: A | O62: MECHANISM | P62: empirical | Q62: environmental psych | R62: causal | S62: medium | T62: Nature interaction improves directed-attention performance. | U62: [to chart] | V62: [to chart] | W62: [to chart] | X62: yes | Y62: partial | Z62: Evidence for recovery spaces/nature contact. | AA62: Environment restores cognition. | AB62: CF-6 | AC62: Workday Interruption Protocol | AE62: Empirical / applied research | AF62: 24 months | AG62: 2026-08-13 | AH62: 2028-08-13 | AI62: Current - re-search on schedule
A63: A4-03 | B63: Scannell & Gifford — Place Attachment (tripartite framework) | C63: https://www.researchgate.net/publication/223552061_Defining_place_attachment_A_tripartite_organizing_framework | D63: https://doi.org/10.1016/j.jenvp.2009.09.006 | E63: ResearchGate / DOI landing | F63: Located - readable or request source | G63: Source located; DOI landing recorded. Check accessible copy during charting. | H63: Scannell & Gifford — Place Attachment (tripartite framework) pdf DOI readable source | I63: https://www.google.com/search?q=Scannell+%26+Gifford+%E2%80%94+Place+Attachment+%28tripartite+framework%29+pdf+DOI+readable+source | J63: 2026-08-13 | K63: Located (not charted) | L63: 4 | M63: WS-E | N63: A | O63: CONSTRUCT/MEASURE | P63: theoretical | Q63: environmental psych | R63: conceptual | S63: high | T63: Place attachment = person + process + place. | U63: [to chart] | V63: [to chart] | W63: [to chart] | X63: partial | Y63: yes | Z63: Operationalize environmental attunement (C3). | AA63: Place is not interchangeable. | AB63: CF-6 | AC63: Cosmotechnic Audit Card | AE63: Empirical / applied research | AF63: 24 months | AG63: 2026-08-13 | AH63: 2028-08-13 | AI63: Current - re-search on schedule
A64: A4-04 | B64: Menatti et al. — Place Attachment & Landscape Restorativeness | C64: https://repositorio.udd.cl/bitstream/11447/6275/1/Place%20attachment%20and%20identification%20as%20predictors%20of%20expected%20landscape%20restorativeness.pdf | D64: https://doi.org/10.1016/j.jenvp.2019.03.005 | E64: Open PDF / DOI landing | F64: Located - readable source | G64: Open repository PDF located. | H64: Menatti et al. — Place Attachment & Landscape Restorativeness pdf DOI readable source | I64: https://www.google.com/search?q=Menatti+et+al.+%E2%80%94+Place+Attachment+%26+Landscape+Restorativeness+pdf+DOI+readable+source | J64: 2026-08-13 | K64: Located (not charted) | L64: 4 | M64: WS-E | N64: A | O64: MEASURE | P64: empirical | Q64: environmental psych | R64: correlational | S64: medium | T64: Person-place bonding raises expected restorativeness. | U64: [to chart] | V64: [to chart] | W64: [to chart] | X64: partial | Y64: yes | Z64: Relation shapes recovery potential. | AA64: Attachment feeds restoration. | AB64: CF-6 | AC64: Technodiversity & Cultural Fit Sheet | AE64: Empirical / applied research | AF64: 24 months | AG64: 2026-08-13 | AH64: 2028-08-13 | AI64: Current - re-search on schedule
A65: A4-05 | B65: Yoon et al. — Perceived Restorativeness & Place Attachment | C65: https://www.frontiersin.org/journals/psychology/articles/10.3389/fpsyg.2023.1201112/pdf | D65: https://doi.org/10.3389/fpsyg.2023.1201112 | E65: Open PDF / DOI landing | F65: Located - readable source | G65: Open Frontiers PDF located. | H65: Yoon et al. — Perceived Restorativeness & Place Attachment pdf DOI readable source | I65: https://www.google.com/search?q=Yoon+et+al.+%E2%80%94+Perceived+Restorativeness+%26+Place+Attachment+pdf+DOI+readable+source | J65: 2026-08-13 | K65: Located (not charted) | L65: 4 | M65: WS-E | N65: A | O65: MEASURE | P65: empirical | Q65: environmental psych | R65: correlational | S65: medium | T65: Perceived restorativeness positively influences place attachment; moderated by sensitivity. | U65: [to chart] | V65: [to chart] | W65: [to chart] | X65: partial | Y65: yes | Z65: Link restorativeness to attunement. | AA65: Restoration and attachment co-vary. | AB65: CF-6 | AC65: Cosmotechnic Audit Card | AE65: Empirical / applied research | AF65: 24 months | AG65: 2026-08-13 | AH65: 2028-08-13 | AI65: Current - re-search on schedule
A66: A4-06 | B66: Chang et al. — Place Attachment & Pro-Environmental Intentions | C66: https://pmc.ncbi.nlm.nih.gov/articles/PMC12832409/ | D66: https://doi.org/10.3389/fpsyg.2025.1678177 | E66: Open full text / DOI landing | F66: Located - readable source | G66: Open PMC/Frontiers source located. | H66: Chang et al. — Place Attachment & Pro-Environmental Intentions pdf DOI readable source | I66: https://www.google.com/search?q=Chang+et+al.+%E2%80%94+Place+Attachment+%26+Pro-Environmental+Intentions+pdf+DOI+readable+source | J66: 2026-08-13 | K66: Located (not charted) | L66: 4 | M66: WS-E | N66: A | O66: TELOS | P66: empirical | Q66: environmental psych | R66: correlational | S66: medium | T66: Place attachment + nature connectedness predict pro-environmental behavior. | U66: [to chart] | V66: [to chart] | W66: [to chart] | X66: no | Y66: yes | Z66: Ecological stake: inhabitation vs extraction. | AA66: Attachment yields care. | AB66: CF-6 | AC66: Anti-Extraction Audit | AE66: Empirical / applied research | AF66: 24 months | AG66: 2026-08-13 | AH66: 2028-08-13 | AI66: Current - re-search on schedule
A67: A4-07 | B67: Hartig et al. — Perceived Restorativeness Scale | C67: https://blogs.ubc.ca/2017wufor200/files/2017/02/Perceived-Restorativeness-Scale-Hartig-et-al-1997.pdf | D67: https://kipdf.com/validation-of-a-measure-of-perceived-environmental-restorativeness-1_5ac406811723dd66fecf6d6e.html | E67: Scale PDF / source text path | F67: Located - readable source | G67: PRS instrument PDF and validation-paper access path located; verify exact Hartig citation during charting. | H67: Hartig et al. — Perceived Restorativeness Scale pdf DOI readable source | I67: https://www.google.com/search?q=Hartig+et+al.+%E2%80%94+Perceived+Restorativeness+Scale+pdf+DOI+readable+source | J67: 2026-08-13 | K67: Pending | L67: 4 | M67: WS-E | N67: B | O67: MEASURE | P67: methods | Q67: environmental psych | R67: conceptual | S67: medium | T67: Validated measure of environmental restorativeness. | U67: [to chart] | V67: [to chart] | W67: [to chart] | X67: partial | Y67: partial | Z67: Candidate measure for C3. | AA67: Restoration is measurable. | AC67: Phenomenological Registration Sheet | AE67: Empirical / applied research | AF67: 24 months | AG67: 2026-08-13 | AH67: 2028-08-13 | AI67: Current - re-search on schedule
A68: A4-08 | B68: Korpela — restorative environments & self-regulation | C68: https://aaltodoc.aalto.fi/bitstreams/006d5f9f-b0e8-42fe-accb-15491d28b58e/download | D68: https://doi.org/10.1006/jevp.2002.0277 | E68: Open PDF / DOI landing | F68: Located - readable source | G68: Aalto repository PDF and DOI landing located. | H68: Korpela — restorative environments & self-regulation pdf DOI readable source | I68: https://www.google.com/search?q=Korpela+%E2%80%94+restorative+environments+%26+self-regulation+pdf+DOI+readable+source | J68: 2026-08-13 | K68: Pending | L68: 4 | M68: WS-C | N68: B | O68: MECHANISM | P68: empirical | Q68: environmental psych | R68: correlational | S68: medium | T68: Favorite places support affect regulation. | U68: [to chart] | V68: [to chart] | W68: [to chart] | X68: partial | Y68: partial | Z68: Link place to emotion regulation (M3). | AA68: Place regulates affect. | AC68: Monstare Protocol vNext | AE68: Empirical / applied research | AF68: 24 months | AG68: 2026-08-13 | AH68: 2028-08-13 | AI68: Current - re-search on schedule
A69: A4-09 | B69: Lewicka — Place Attachment: 40 years | C69: https://docslib.org/doc/6265744/place-attachment-how-far-have-we-come-in-the-last-40-years | D69: https://doi.org/10.1016/j.jenvp.2010.10.001 | E69: Readable HTML/PDF mirror / DOI landing | F69: Located - readable source | G69: Readable copy and DOI located; prefer legal institutional access if available. | H69: Lewicka — Place Attachment: 40 years pdf DOI readable source | I69: https://www.google.com/search?q=Lewicka+%E2%80%94+Place+Attachment%3A+40+years+pdf+DOI+readable+source | J69: 2026-08-13 | K69: Pending | L69: 4 | M69: WS-E | N69: B | O69: REVIEW | P69: review | Q69: environmental psych | R69: conceptual | S69: low | T69: Major review of place attachment literature. | U69: [to chart] | V69: [to chart] | W69: [to chart] | X69: no | Y69: partial | Z69: Orientation for the construct. | AA69: Breadth of place research. | AC69: Construct Dictionary | AE69: Empirical / applied research | AF69: 24 months | AG69: 2026-08-13 | AH69: 2028-08-13 | AI69: Current - re-search on schedule
A70: A4-10 | B70: Gibson — The Ecological Approach to Visual Perception | C70: https://archive.org/details/ecologicalapproa0000gibs | D70: https://www.routledge.com/The-Ecological-Approach-to-Visual-Perception/Gibson/p/book/9781848725782 | E70: Archive lending / publisher landing | F70: Located - restricted readable | G70: Archive lending path located; use legal borrowed/purchased copy for charting. | H70: Gibson — The Ecological Approach to Visual Perception pdf DOI readable source | I70: https://www.google.com/search?q=Gibson+%E2%80%94+The+Ecological+Approach+to+Visual+Perception+pdf+DOI+readable+source | J70: 2026-08-13 | K70: Pending | L70: 4 | M70: WS-E | N70: B | O70: TELOS/MECHANISM | P70: theoretical | Q70: perception | R70: conceptual | S70: medium | T70: Affordances; perception geared to situated action. | U70: [to chart] | V70: [to chart] | W70: [to chart] | X70: partial | Y70: partial | Z70: Ground situated action/affordances. | AA70: Environment offers action. | AC70: Arousal/Flow/Task-Switching Layer | AE70: General supporting source | AF70: 36 months | AG70: 2026-08-13 | AH70: 2029-08-13 | AI70: Current - located, access/fit caveat
A71: A5-01 | B71: Varela — Neurophenomenology | C71: https://docslib.org/doc/729945/neurophenomenology-a-methodological-remedy-for-the-hard-problem-francisco-j | D71: https://www.ingentaconnect.com/content/imp/jcs/1996/00000003/00000004/718 | E71: Open HTML/PDF mirror / publisher landing | F71: Located - readable source | G71: Readable copy located; publisher landing recorded. | H71: Varela — Neurophenomenology pdf DOI readable source | I71: https://www.google.com/search?q=Varela+%E2%80%94+Neurophenomenology+pdf+DOI+readable+source | J71: 2026-08-13 | K71: Located (not charted) | L71: 5 | M71: WS-F | N71: A | O71: METHOD/TELOS | P71: theoretical | Q71: cognitive science | R71: conceptual | S71: high | T71: Cognitive science needs disciplined first-person methods. | U71: [to chart] | V71: [to chart] | W71: [to chart] | X71: no | Y71: yes | Z71: Justify phenomenological capture alongside metrics. | AA71: Experience is data too. | AB71: CF-2 | AC71: Phenomenological Registration Sheet | AD71: OC-4 | AE71: Philosophical / historical / theoretical | AF71: 60 months | AG71: 2026-08-13 | AH71: 2031-08-13 | AI71: Current - re-search on schedule
A72: A5-02 | B72: Petitmengin — Describing Experience in the Second Person | C72: https://clairepetitmengin.fr/AArticles%20versions%20finales/PCS%20-%20Second%20Person.pdf | D72: https://link.springer.com/article/10.1007/s11097-006-9022-2 | E72: Open author PDF / DOI landing | F72: Located - readable source | G72: Author PDF located. | H72: Petitmengin — Describing Experience in the Second Person pdf DOI readable source | I72: https://www.google.com/search?q=Petitmengin+%E2%80%94+Describing+Experience+in+the+Second+Person+pdf+DOI+readable+source | J72: 2026-08-13 | K72: Located (not charted) | L72: 5 | M72: WS-F | N72: A | O72: METHOD | P72: methods | Q72: phenomenology | R72: conceptual | S72: high | T72: Micro-phenomenological interview evokes specific lived episodes. | U72: [to chart] | V72: [to chart] | W72: [to chart] | X72: no | Y72: yes | Z72: Design episode-evoking prompts, not opinion prompts. | AA72: Preserve fine-grained experience. | AB72: CF-2 | AC72: Phenomenological Registration Sheet | AE72: Methods / reporting standards | AF72: 36 months | AG72: 2026-08-13 | AH72: 2029-08-13 | AI72: Current - re-search on schedule
A73: A5-03 | B73: Petitmengin et al. — micro-phenomenology studies | C73: https://hal.science/hal-02264833v1/file/PCS%20-%20Article%20analyse.pdf | D73: https://doi.org/10.1007/s11097-018-9597-4 | E73: Open PDF / DOI landing | F73: Located - readable source | G73: Open HAL PDF located for micro-phenomenological analysis method. | H73: Petitmengin et al. — micro-phenomenology studies pdf DOI readable source | I73: https://www.google.com/search?q=Petitmengin+et+al.+%E2%80%94+micro-phenomenology+studies+pdf+DOI+readable+source | J73: 2026-08-13 | K73: Located (not charted) | L73: 5 | M73: WS-F | N73: A | O73: METHOD/EMPIRICAL | P73: empirical | Q73: phenomenology | R73: correlational | S73: medium | T73: Fine-grained description can become usable evidence. | U73: [to chart] | V73: [to chart] | W73: [to chart] | X73: no | Y73: partial | Z73: Capture onset/transition/arousal experience. | AA73: Description yields signal. | AC73: Phenomenological Registration Sheet | AE73: Empirical / applied research | AF73: 24 months | AG73: 2026-08-13 | AH73: 2028-08-13 | AI73: Current - re-search on schedule
A74: A5-04 | B74: Valenzuela-Moguillansky & Vasquez-Rosati — Analysis Procedure | C74: https://constructivist.info/14/2/123.valenzuela.pdf | D74: https://constructivist.info/14/2/123 | E74: Open PDF / landing | F74: Located - readable source | G74: Open Constructivist Foundations PDF located. | H74: Valenzuela-Moguillansky & Vasquez-Rosati — Analysis Procedure pdf DOI readable source | I74: https://www.google.com/search?q=Valenzuela-Moguillansky+%26+Vasquez-Rosati+%E2%80%94+Analysis+Procedure+pdf+DOI+readable+source | J74: 2026-08-13 | K74: Located (not charted) | L74: 5 | M74: WS-F | N74: A | O74: METHOD/ANALYSIS | P74: methods | Q74: phenomenology | R74: conceptual | S74: medium | T74: Stepwise analysis procedure for micro-phenomenological data. | U74: [to chart] | V74: [to chart] | W74: [to chart] | X74: no | Y74: partial | Z74: Analyze registration notes without flattening them. | AA74: Structured, non-reductive analysis. | AB74: CF-2 | AC74: Phenomenological Registration Sheet | AD74: OC-4 | AE74: Methods / reporting standards | AF74: 36 months | AG74: 2026-08-13 | AH74: 2029-08-13 | AI74: Current - re-search on schedule
A75: A5-05 | B75: Hurlburt & Heavey — Descriptive Experience Sampling | C75: http://www.hurlburt.faculty.unlv.edu/hurlburt-akhter-2006.pdf | D75: https://archive.org/details/exploringinnerex0000hurl | E75: Open PDF / archive landing | F75: Located - readable source | G75: DES method PDF and book archive located. | H75: Hurlburt & Heavey — Descriptive Experience Sampling pdf DOI readable source | I75: https://www.google.com/search?q=Hurlburt+%26+Heavey+%E2%80%94+Descriptive+Experience+Sampling+pdf+DOI+readable+source | J75: 2026-08-13 | K75: Located (not charted) | L75: 5 | M75: WS-F | N75: A | O75: METHOD | P75: methods | Q75: psychology | R75: conceptual | S75: medium | T75: Sampling near occurrence reduces retrospective bias. | U75: [to chart] | V75: [to chart] | W75: [to chart] | X75: partial | Y75: partial | Z75: Semi-random in-the-moment state capture. | AA75: Moment over narrative. | AB75: CF-2 | AC75: Phenomenological Registration Sheet | AE75: Empirical / applied research | AF75: 24 months | AG75: 2026-08-13 | AH75: 2028-08-13 | AI75: Current - re-search on schedule
A76: A5-06 | B76: Bass-Krueger et al. — DES vs Micro-Phenomenological Interviews | C76: https://www.indecs.eu/2024/indecs2024-pp84-106.pdf | D76: https://hrcak.srce.hr/en/clanak/454680 | E76: Open PDF / journal landing | F76: Located - readable source | G76: Open INDECS PDF located. | H76: Bass-Krueger et al. — DES vs Micro-Phenomenological Interviews pdf DOI readable source | I76: https://www.google.com/search?q=Bass-Krueger+et+al.+%E2%80%94+DES+vs+Micro-Phenomenological+Interviews+pdf+DOI+readable+source | J76: 2026-08-13 | K76: Located (not charted) | L76: 5 | M76: WS-F | N76: A | O76: METHOD/COMPARISON | P76: empirical | Q76: phenomenology | R76: correlational | S76: medium | T76: Compares two first-person methods relevant to Monstare. | U76: [to chart] | V76: [to chart] | W76: [to chart] | X76: no | Y76: partial | Z76: Choose immediate sampling vs episode interview. | AA76: Method fit to moment. | AC76: Phenomenological Registration Sheet | AE76: Empirical / applied research | AF76: 24 months | AG76: 2026-08-13 | AH76: 2028-08-13 | AI76: Current - re-search on schedule
A77: A5-07 | B77: Depraz, Varela & Vermersch — On Becoming Aware | C77: https://openlibrary.org/books/OL3570652M/On_becoming_aware | D77: https://benjamins.com/catalog/aicr.43 | E77: Open Library/catalog / publisher landing | F77: Located - restricted/source landing | G77: Book access located via Open Library/catalog and John Benjamins landing; no open full text recorded. | H77: Depraz, Varela & Vermersch — On Becoming Aware pdf DOI readable source | I77: https://www.google.com/search?q=Depraz%2C+Varela+%26+Vermersch+%E2%80%94+On+Becoming+Aware+pdf+DOI+readable+source | J77: 2026-08-13 | K77: Pending | L77: 5 | M77: WS-F | N77: B | O77: METHOD/TELOS | P77: theoretical | Q77: phenomenology | R77: conceptual | S77: medium | T77: Practice of becoming aware of experience. | U77: [to chart] | V77: [to chart] | W77: [to chart] | X77: no | Y77: partial | Z77: Grounding for awareness practice. | AA77: Awareness is trainable. | AC77: Phenomenological Registration Sheet | AE77: Philosophical / historical / theoretical | AF77: 60 months | AG77: 2026-08-13 | AH77: 2031-08-13 | AI77: Current - located, access/fit caveat
A78: A5-08 | B78: Csikszentmihalyi & Larson — Experience Sampling Method | C78: https://link.springer.com/content/pdf/10.1007/978-94-017-9088-8_3.pdf | D78: https://doi.org/10.1007/978-94-017-9088-8_3 | E78: Open Springer chapter PDF / DOI landing | F78: Located - readable source | G78: Csikszentmihalyi & Larson ESM reliability/validity chapter located. | H78: Csikszentmihalyi & Larson — Experience Sampling Method pdf DOI readable source | I78: https://www.google.com/search?q=Csikszentmihalyi+%26+Larson+%E2%80%94+Experience+Sampling+Method+pdf+DOI+readable+source | J78: 2026-08-13 | K78: Pending | L78: 5 | M78: WS-F | N78: B | O78: METHOD | P78: methods | Q78: psychology | R78: conceptual | S78: low | T78: Classic ESM foundation. | U78: [to chart] | V78: [to chart] | W78: [to chart] | X78: partial | Y78: no | Z78: ESM basis for engagement capture. | AA78: Sample lived time. | AC78: Digital Capture Architecture | AE78: Empirical / applied research | AF78: 24 months | AG78: 2026-08-13 | AH78: 2028-08-13 | AI78: Current - re-search on schedule
A79: A5-09 | B79: Zahavi — Subjectivity and Selfhood | C79: https://direct.mit.edu/books/monograph/2097/Subjectivity-and-SelfhoodInvestigating-the-First | D79: https://mitpress.mit.edu/9780262740340/subjectivity-and-selfhood/ | E79: Publisher/direct book landing | F79: Located - source landing | G79: MIT Press landing/direct page located; use legal library/e-book access for charting. | H79: Zahavi — Subjectivity and Selfhood pdf DOI readable source | I79: https://www.google.com/search?q=Zahavi+%E2%80%94+Subjectivity+and+Selfhood+pdf+DOI+readable+source | J79: 2026-08-13 | K79: Pending | L79: 5 | M79: WS-F | N79: B | O79: PHENOMENOLOGY/TELOS | P79: philosophical | Q79: phenomenology | R79: conceptual | S79: medium | T79: First-person givenness and self-experience. | U79: [to chart] | V79: [to chart] | W79: [to chart] | X79: no | Y79: partial | Z79: Clarify the self that is captured. | AA79: Selfhood before scores. | AC79: Construct Dictionary | AE79: Philosophical / historical / theoretical | AF79: 60 months | AG79: 2026-08-13 | AH79: 2031-08-13 | AI79: Current - located, access/fit caveat
A80: A5-10 | B80: Gallagher & Zahavi — The Phenomenological Mind | C80: https://archive.org/details/phenomenological0000gall | D80: https://digitalcommons.memphis.edu/facpubs/6410/ | E80: Archive lending / faculty publication landing | F80: Located - restricted readable | G80: Archive lending and faculty publication page located. | H80: Gallagher & Zahavi — The Phenomenological Mind pdf DOI readable source | I80: https://www.google.com/search?q=Gallagher+%26+Zahavi+%E2%80%94+The+Phenomenological+Mind+pdf+DOI+readable+source | J80: 2026-08-13 | K80: Pending | L80: 5 | M80: WS-F | N80: B | O80: TELOS/METHOD | P80: review | Q80: phenomenology | R80: conceptual | S80: low | T80: Bridge between phenomenology and cognitive science. | U80: [to chart] | V80: [to chart] | W80: [to chart] | X80: no | Y80: partial | Z80: Accessible bridge for the team. | AA80: Phenomenology meets cogsci. | AC80: Construct Dictionary | AE80: Empirical / applied research | AF80: 24 months | AG80: 2026-08-13 | AH80: 2028-08-13 | AI80: Current - located, access/fit caveat
A81: A6-01 | B81: Laitinen & Sahlgren — AI Systems and Respect for Human Autonomy | C81: https://trepo.tuni.fi/bitstream/handle/10024/220970/AI_systems_Laitinen_Sahlgren.pdf?sequence=1 | D81: https://www.frontiersin.org/journals/artificial-intelligence/articles/10.3389/frai.2021.705164/full | E81: Open PDF and open full text | F81: Readable source found | G81: Frontiers in Artificial Intelligence 2021, DOI 10.3389/frai.2021.705164. | H81: Laitinen & Sahlgren — AI Systems and Respect for Human Autonomy pdf DOI readable source | I81: https://www.google.com/search?q=Laitinen+%26+Sahlgren+%E2%80%94+AI+Systems+and+Respect+for+Human+Autonomy+pdf+DOI+readable+source | J81: 2026-08-13 | K81: Pending | L81: 6 | M81: WS-H | N81: A | O81: ETHICS/DESIGN/MEASURE | P81: theoretical | Q81: AI ethics | R81: conceptual | S81: high | T81: Multidimensional model of autonomy; how AI supports or hinders it. | U81: [to chart] | V81: [to chart] | W81: [to chart] | X81: partial | Y81: yes | Z81: Autonomy audit for AI/automation. | AA81: Core of the M7 audit. | AB81: CF-4 | AC81: Agency & Autonomy Checklist | AD81: OC-8 | AE81: Fast-moving digital/AI/work trend | AF81: 6 months | AG81: 2026-08-13 | AH81: 2027-02-13 | AI81: Current - re-search on schedule
A82: A6-02 | B82: AI and Human Autonomy: A Literature Review | C82: https://link.springer.com/content/pdf/10.1007/s43681-025-00958-4.pdf | D82: https://link.springer.com/article/10.1007/s43681-025-00958-4 | E82: Open/Springer PDF | F82: Located - readable source | G82: Open Springer PDF located. | H82: AI and Human Autonomy: A Literature Review pdf DOI readable source | I82: https://www.google.com/search?q=AI+and+Human+Autonomy%3A+A+Literature+Review+pdf+DOI+readable+source | J82: 2026-08-13 | K82: Located (not charted) | L82: 6 | M82: WS-H | N82: A | O82: REVIEW/ETHICS | P82: review | Q82: AI ethics | R82: conceptual | S82: high | T82: Maps heterogeneous AI-autonomy debates. | U82: [to chart] | V82: [to chart] | W82: [to chart] | X82: no | Y82: yes | Z82: Map autonomy risks before agentic supports. | AA82: Autonomy risk landscape. | AB82: CF-4 | AC82: Agency & Autonomy Checklist | AE82: Fast-moving digital/AI/work trend | AF82: 6 months | AG82: 2026-08-13 | AH82: 2027-02-13 | AI82: Current - re-search on schedule
A83: A6-03 | B83: Shneiderman — Human-Centered AI | C83: https://arxiv.org/pdf/2002.04087 | D83: https://doi.org/10.1145/3419764 | E83: Open PDF / DOI landing | F83: Located - readable source | G83: Arxiv PDF and DOI landing located. | H83: Shneiderman — Human-Centered AI pdf DOI readable source | I83: https://www.google.com/search?q=Shneiderman+%E2%80%94+Human-Centered+AI+pdf+DOI+readable+source | J83: 2026-08-13 | K83: Located (not charted) | L83: 6 | M83: WS-H | N83: A | O83: DESIGN/ETHICS | P83: theoretical | Q83: HCI/AI | R83: conceptual | S83: high | T83: Reliable, safe, trustworthy AI with high human control. | U83: [to chart] | V83: [to chart] | W83: [to chart] | X83: partial | Y83: yes | Z83: High human control; clear tool boundaries. | AA83: Human agency at the center. | AB83: CF-4 | AC83: AI Assistant Use Rules | AE83: Fast-moving digital/AI/work trend | AF83: 6 months | AG83: 2026-08-13 | AH83: 2027-02-13 | AI83: Current - re-search on schedule
A84: A6-04 | B84: Parasuraman & Riley — Use, Misuse, Disuse, Abuse | C84: https://web.mit.edu/16.459/www/parasuraman.pdf?source=post_page--------------------------- | D84: https://doi.org/10.1518/001872097778543886 | E84: Open PDF copy / publisher DOI | F84: Readable source found | G84: Human Factors 1997; DOI 10.1518/001872097778543886. | H84: Parasuraman & Riley — Use, Misuse, Disuse, Abuse pdf DOI readable source | I84: https://www.google.com/search?q=Parasuraman+%26+Riley+%E2%80%94+Use%2C+Misuse%2C+Disuse%2C+Abuse+pdf+DOI+readable+source | J84: 2026-08-13 | K84: Pending | L84: 6 | M84: WS-H | N84: A | O84: WARNING/MECHANISM | P84: review | Q84: human factors | R84: conceptual | S84: high | T84: Taxonomy of automation reliance failures. | U84: [to chart] | V84: [to chart] | W84: [to chart] | X84: partial | Y84: partial | Z84: Distinguish helpful reliance from dependency/disuse. | AA84: Reliance can degrade. | AB84: CF-4 | AC84: AI Assistant Use Rules | AE84: Empirical / applied research | AF84: 24 months | AG84: 2026-08-13 | AH84: 2028-08-13 | AI84: Current - re-search on schedule
A85: A6-05 | B85: Parasuraman, Sheridan & Wickens — Levels of Automation | C85: https://www.researchgate.net/profile/Raja-Parasuraman/publication/11596569_A_model_for_types_and_levels_of_human_interaction_with_automation_IEEE_Trans_Syst_Man_Cybern_Part_A_Syst_Hum_303_286-297/links/0fcfd50c098e2edd75000000/A-model-for-types-and-levels-of-human-interaction-with-automation-IEEE-Trans-Syst-Man-Cybern-Part-A-Syst-Hum-303-286-297.pdf | D85: https://ieeexplore.ieee.org/document/844354 | E85: ResearchGate PDF / IEEE landing | F85: Located - readable source | G85: PDF copy located; IEEE landing recorded. | H85: Parasuraman, Sheridan & Wickens — Levels of Automation pdf DOI readable source | I85: https://www.google.com/search?q=Parasuraman%2C+Sheridan+%26+Wickens+%E2%80%94+Levels+of+Automation+pdf+DOI+readable+source | J85: 2026-08-13 | K85: Located (not charted) | L85: 6 | M85: WS-H | N85: A | O85: DESIGN/METHOD | P85: theoretical | Q85: human factors | R85: conceptual | S85: medium | T85: Types-and-levels framework for human-automation interaction. | U85: [to chart] | V85: [to chart] | W85: [to chart] | X85: partial | Y85: partial | Z85: Decide what to automate vs author. | AA85: Calibrate automation level. | AB85: CF-4 | AC85: AI Assistant Use Rules | AD85: OC-3 | AE85: Fast-moving digital/AI/work trend | AF85: 6 months | AG85: 2026-08-13 | AH85: 2027-02-13 | AI85: Current - re-search on schedule
A86: A6-06 | B86: Eubanks — Automating Inequality | C86: https://archive.org/details/automatinginequa0000euba | D86: https://us.macmillan.com/books/9781250074317/automatinginequality | E86: Archive lending / publisher landing | F86: Located - restricted readable | G86: Archive lending/publisher page located. | H86: Eubanks — Automating Inequality pdf DOI readable source | I86: https://www.google.com/search?q=Eubanks+%E2%80%94+Automating+Inequality+pdf+DOI+readable+source | J86: 2026-08-13 | K86: Located (not charted) | L86: 6 | M86: WS-L | N86: A | O86: WARNING/ETHICS | P86: empirical | Q86: STS/policy | R86: correlational | S86: medium | T86: Automated systems encode harm and governance power. | U86: [to chart] | V86: [to chart] | W86: [to chart] | X86: no | Y86: yes | Z86: Caution against invisible decision systems. | AA86: Automation can harm invisibly. | AB86: CF-4 | AC86: Design Veto Catalogue | AE86: Empirical / applied research | AF86: 24 months | AG86: 2026-08-13 | AH86: 2028-08-13 | AI86: Current - located, access/fit caveat
A87: A6-07 | B87: Nissenbaum — Privacy in Context | C87: https://archive.org/details/privacyincontext0000niss | D87: https://www.sup.org/books/law/privacy-context | E87: Archive lending / publisher landing | F87: Located - restricted readable | G87: Archive lending and Stanford University Press landing located. | H87: Nissenbaum — Privacy in Context pdf DOI readable source | I87: https://www.google.com/search?q=Nissenbaum+%E2%80%94+Privacy+in+Context+pdf+DOI+readable+source | J87: 2026-08-13 | K87: Pending | L87: 6 | M87: WS-H | N87: B | O87: ETHICS/DESIGN | P87: theoretical | Q87: info ethics | R87: conceptual | S87: medium | T87: Contextual integrity governs appropriate data flows. | U87: [to chart] | V87: [to chart] | W87: [to chart] | X87: no | Y87: yes | Z87: Contextual integrity for capture. | AA87: Data has contextual norms. | AB87: CF-2 | AC87: Digital Capture Architecture | AE87: General supporting source | AF87: 36 months | AG87: 2026-08-13 | AH87: 2029-08-13 | AI87: Current - located, access/fit caveat
A88: A6-08 | B88: Mittelstadt et al. — The Ethics of Algorithms | C88: https://www.sfu.ca/~palys/MittelstadtEtAl-2016-TheEthicsOfAlgorithms.pdf | D88: https://doi.org/10.1177/2053951716679679 | E88: Open PDF / DOI landing | F88: Located - readable source | G88: Open PDF and DOI located. | H88: Mittelstadt et al. — The Ethics of Algorithms pdf DOI readable source | I88: https://www.google.com/search?q=Mittelstadt+et+al.+%E2%80%94+The+Ethics+of+Algorithms+pdf+DOI+readable+source | J88: 2026-08-13 | K88: Pending | L88: 6 | M88: WS-L | N88: B | O88: ETHICS/WARNING | P88: review | Q88: AI ethics | R88: conceptual | S88: medium | T88: Opacity, responsibility, bias, autonomy concerns. | U88: [to chart] | V88: [to chart] | W88: [to chart] | X88: no | Y88: yes | Z88: Checklist of algorithmic harms. | AA88: Opacity threatens autonomy. | AB88: CF-4 | AC88: Design Veto Catalogue | AE88: Fast-moving digital/AI/work trend | AF88: 6 months | AG88: 2026-08-13 | AH88: 2027-02-13 | AI88: Current - re-search on schedule
A89: A6-09 | B89: Wachter, Mittelstadt & Floridi — transparent/explainable AI | C89: https://discovery.ucl.ac.uk/id/eprint/10038294/ | D89: https://doi.org/10.1126/scirobotics.aan6080 | E89: Open repository / DOI landing | F89: Located - readable source | G89: UCL accepted manuscript and Science Robotics DOI located. | H89: Wachter, Mittelstadt & Floridi — transparent/explainable AI pdf DOI readable source | I89: https://www.google.com/search?q=Wachter%2C+Mittelstadt+%26+Floridi+%E2%80%94+transparent%2Fexplainable+AI+pdf+DOI+readable+source | J89: 2026-08-13 | K89: Pending | L89: 6 | M89: WS-H | N89: B | O89: ETHICS/DESIGN | P89: theoretical | Q89: AI governance | R89: conceptual | S89: low | T89: Transparency/explanation in automated decisions. | U89: [to chart] | V89: [to chart] | W89: [to chart] | X89: no | Y89: partial | Z89: Explainability requirements. | AA89: Explanation supports agency. | AB89: CF-4 | AC89: AI Assistant Use Rules | AE89: Fast-moving digital/AI/work trend | AF89: 6 months | AG89: 2026-08-13 | AH89: 2027-02-13 | AI89: Current - re-search on schedule
A90: A6-10 | B90: Calo — Robotics and the Lessons of Cyberlaw | C90: https://techpolicylab.uw.edu/wp-content/uploads/2018/06/Robotics-Lessons-Cyberlaw-Calo.pdf | D90: https://digitalcommons.law.uw.edu/faculty-articles/23/ | E90: Open PDF / faculty repository landing | F90: Located - readable source | G90: University-hosted PDF and UW faculty repository located. | H90: Calo — Robotics and the Lessons of Cyberlaw pdf DOI readable source | I90: https://www.google.com/search?q=Calo+%E2%80%94+Robotics+and+the+Lessons+of+Cyberlaw+pdf+DOI+readable+source | J90: 2026-08-13 | K90: Pending | L90: 6 | M90: WS-L | N90: B | O90: ETHICS/GOVERNANCE | P90: theoretical | Q90: law/tech | R90: conceptual | S90: low | T90: Governance lessons for embodied/automated systems. | U90: [to chart] | V90: [to chart] | W90: [to chart] | X90: no | Y90: partial | Z90: Governance framing. | AA90: Law shapes tool use. | AC90: Master Research Index | AE90: Fast-moving digital/AI/work trend | AF90: 6 months | AG90: 2026-08-13 | AH90: 2027-02-13 | AI90: Current - re-search on schedule
A91: A7-01 | B91: Risko & Gilbert — Cognitive Offloading | C91: https://discovery.ucl.ac.uk/id/eprint/1508770/1/gilbert_TiCS_OFFLOADING_RPS.pdf | D91: https://doi.org/10.1016/j.tics.2016.07.002 | E91: Open PDF / DOI landing | F91: Located - readable source | G91: Open UCL PDF located. | H91: Risko & Gilbert — Cognitive Offloading pdf DOI readable source | I91: https://www.google.com/search?q=Risko+%26+Gilbert+%E2%80%94+Cognitive+Offloading+pdf+DOI+readable+source | J91: 2026-08-13 | K91: Located (not charted) | L91: 7 | M91: WS-B | N91: A | O91: MECHANISM/WARNING | P91: review | Q91: cognitive science | R91: conceptual | S91: high | T91: Using external aids to reduce cognitive demand; adaptive vs atrophy. | U91: [to chart] | V91: [to chart] | W91: [to chart] | X91: partial | Y91: yes | Z91: Distinguish adaptive offloading from atrophy. | AA91: Offloading has a cost. | AB91: CF-3 | AC91: AI Assistant Use Rules | AD91: OC-13 | AE91: Empirical / applied research | AF91: 24 months | AG91: 2026-08-13 | AH91: 2028-08-13 | AI91: Current - re-search on schedule
A92: A7-02 | B92: Sparrow, Liu & Wegner — Google Effects on Memory | C92: https://pubmed.ncbi.nlm.nih.gov/21764755/ | D92: https://www.science.org/doi/10.1126/science.1207745 | E92: PubMed / DOI landing | F92: Located - source landing | G92: PubMed and Science DOI located; use institutional/legal access for final full text. | H92: Sparrow, Liu & Wegner — Google Effects on Memory pdf DOI readable source | I92: https://www.google.com/search?q=Sparrow%2C+Liu+%26+Wegner+%E2%80%94+Google+Effects+on+Memory+pdf+DOI+readable+source | J92: 2026-08-13 | K92: Located (not charted) | L92: 7 | M92: WS-H | N92: A | O92: WARNING | P92: empirical | Q92: psychology | R92: causal | S92: high | T92: Expecting external availability changes what is remembered. | U92: [to chart] | V92: [to chart] | W92: [to chart] | X92: partial | Y92: partial | Z92: External memory reshapes recall. | AA92: Availability alters memory. | AB92: CF-3 | AC92: AI Assistant Use Rules | AE92: Empirical / applied research | AF92: 24 months | AG92: 2026-08-13 | AH92: 2028-08-13 | AI92: Current - located, access/fit caveat
A93: A7-03 | B93: Zhu et al. — Dependent vs Autonomous Offloading to GenAI | C93: https://www.frontiersin.org/journals/psychology/articles/10.3389/fpsyg.2026.1878629/pdf | D93: https://pubmed.ncbi.nlm.nih.gov/42534412/ | E93: Open PDF / PubMed | F93: Located - readable source | G93: Open Frontiers/PubMed source located. | H93: Zhu et al. — Dependent vs Autonomous Offloading to GenAI pdf DOI readable source | I93: https://www.google.com/search?q=Zhu+et+al.+%E2%80%94+Dependent+vs+Autonomous+Offloading+to+GenAI+pdf+DOI+readable+source | J93: 2026-08-13 | K93: Located (not charted) | L93: 7 | M93: WS-H | N93: A | O93: EMPIRICAL/DESIGN | P93: empirical | Q93: HCI/AI | R93: correlational | S93: high | T93: Distinguishes dependent from autonomous offloading to generative AI. | U93: [to chart] | V93: [to chart] | W93: [to chart] | X93: partial | Y93: yes | Z93: Direct rule: scaffold thinking without transferring agency. | AA93: Autonomous vs dependent offloading. | AB93: CF-3 | AC93: AI Assistant Use Rules | AD93: OC-13 | AE93: Fast-moving digital/AI/work trend | AF93: 6 months | AG93: 2026-08-13 | AH93: 2027-02-13 | AI93: Current - re-search on schedule
A94: A7-04 | B94: Chirayath et al. — Cognitive Offloading or Overload? | C94: https://public-pages-files-2025.frontiersin.org/journals/psychology/articles/10.3389/fpsyg.2025.1699320/pdf | D94: https://doi.org/10.3389/fpsyg.2025.1699320 | E94: Open PDF / DOI landing | F94: Located - readable source | G94: Open Frontiers PDF located. | H94: Chirayath et al. — Cognitive Offloading or Overload? pdf DOI readable source | I94: https://www.google.com/search?q=Chirayath+et+al.+%E2%80%94+Cognitive+Offloading+or+Overload%3F+pdf+DOI+readable+source | J94: 2026-08-13 | K94: Located (not charted) | L94: 7 | M94: WS-I | N94: A | O94: WARNING/DESIGN | P94: theoretical | Q94: cognitive science | R94: conceptual | S94: medium | T94: AI as coping support and overload/dependency risk. | U94: [to chart] | V94: [to chart] | W94: [to chart] | X94: partial | Y94: yes | Z94: Anti-overreliance; hypermonitoring risk. | AA94: Support can become overload. | AB94: CF-3 | AC94: Motivation Crowding Watch Card | AE94: General supporting source | AF94: 36 months | AG94: 2026-08-13 | AH94: 2029-08-13 | AI94: Current - re-search on schedule
A95: A7-05 | B95: Molenaar — Regulation of Learning and AI | C95: https://doaj.org/article/e98b82c211794158848a4c1363de1847 | D95: https://doi.org/10.1016/j.caeai.2022.100070 | E95: DOAJ / DOI landing | F95: Located - readable source | G95: DOAJ/ScienceDirect open access record located. | H95: Molenaar — Regulation of Learning and AI pdf DOI readable source | I95: https://www.google.com/search?q=Molenaar+%E2%80%94+Regulation+of+Learning+and+AI+pdf+DOI+readable+source | J95: 2026-08-13 | K95: Located (not charted) | L95: 7 | M95: WS-B | N95: A | O95: MECHANISM/DESIGN | P95: theoretical | Q95: learning sciences | R95: conceptual | S95: medium | T95: Distinguishes shared regulation from AI taking over regulation. | U95: [to chart] | V95: [to chart] | W95: [to chart] | X95: partial | Y95: yes | Z95: AI as coach, not governor. | AA95: Hybrid regulation, not takeover. | AB95: CF-4 | AC95: AI Assistant Use Rules | AE95: Fast-moving digital/AI/work trend | AF95: 6 months | AG95: 2026-08-13 | AH95: 2027-02-13 | AI95: Current - re-search on schedule
A96: A7-06 | B96: Zimmerman — Self-Regulated Learning | C96: https://www.leiderschapsdomeinen.nl/wp-content/uploads/2016/12/Zimmerman-B.-2002-Becoming-Self-Regulated-Learner.pdf | D96: https://doi.org/10.1207/S15430421TIP4102_2 | E96: Open PDF / DOI landing | F96: Located - readable source | G96: Open PDF located. | H96: Zimmerman — Self-Regulated Learning pdf DOI readable source | I96: https://www.google.com/search?q=Zimmerman+%E2%80%94+Self-Regulated+Learning+pdf+DOI+readable+source | J96: 2026-08-13 | K96: Located (not charted) | L96: 7 | M96: WS-B | N96: A | O96: MECHANISM | P96: theoretical | Q96: educational psych | R96: conceptual | S96: medium | T96: Forethought, performance, reflection cycle. | U96: [to chart] | V96: [to chart] | W96: [to chart] | X96: yes | Y96: partial | Z96: Ensure AI does not bypass planning/monitoring/reflection. | AA96: Preserve the SRL cycle. | AB96: CF-3 | AC96: AI Assistant Use Rules | AE96: General supporting source | AF96: 36 months | AG96: 2026-08-13 | AH96: 2029-08-13 | AI96: Current - re-search on schedule
A97: A7-07 | B97: Salomon, Perkins & Globerson — Partners in Cognition | C97: http://www.acousticslab.org/dots_sample/module5/SalomonEtAl1991.pdf | D97: https://doi.org/10.3102/0013189X020003002 | E97: Open PDF / DOI landing | F97: Located - readable source | G97: Readable PDF and DOI located. | H97: Salomon, Perkins & Globerson — Partners in Cognition pdf DOI readable source | I97: https://www.google.com/search?q=Salomon%2C+Perkins+%26+Globerson+%E2%80%94+Partners+in+Cognition+pdf+DOI+readable+source | J97: 2026-08-13 | K97: Pending | L97: 7 | M97: WS-B | N97: B | O97: TELOS/DESIGN | P97: theoretical | Q97: cognitive science | R97: conceptual | S97: medium | T97: Effects with vs effects of intelligent technologies. | U97: [to chart] | V97: [to chart] | W97: [to chart] | X97: partial | Y97: partial | Z97: Seek durable 'effects of' not just 'effects with'. | AA97: Tools should leave capacity behind. | AB97: CF-3 | AC97: AI Assistant Use Rules | AE97: General supporting source | AF97: 36 months | AG97: 2026-08-13 | AH97: 2029-08-13 | AI97: Current - re-search on schedule
A98: A7-08 | B98: Kirsh — The Intelligent Use of Space | C98: https://adrenaline.ucsd.edu/kirsh/Articles/Space/intelligent_useof_space.pdf | D98: https://adrenaline.ucsd.edu/kirsh/Articles/Space/AIJ1.html | E98: Author PDF / author HTML | F98: Located - readable source | G98: UCSD author PDF and HTML located. | H98: Kirsh — The Intelligent Use of Space pdf DOI readable source | I98: https://www.google.com/search?q=Kirsh+%E2%80%94+The+Intelligent+Use+of+Space+pdf+DOI+readable+source | J98: 2026-08-13 | K98: Pending | L98: 7 | M98: WS-E | N98: B | O98: MECHANISM/DESIGN | P98: theoretical | Q98: cognitive science | R98: conceptual | S98: low | T98: Offloading cognition to spatial arrangement. | U98: [to chart] | V98: [to chart] | W98: [to chart] | X98: partial | Y98: partial | Z98: Environmental offloading design. | AA98: Space as cognitive aid. | AC98: Digital Capture Architecture | AE98: General supporting source | AF98: 36 months | AG98: 2026-08-13 | AH98: 2029-08-13 | AI98: Current - re-search on schedule
A99: A7-09 | B99: Oulasvirta — offloading and interface design | C99: https://research.aalto.fi/files/42021453/Oulasvirta_Combinatorial_optimization_of_Graphical_user_interface.pdf | D99: https://www.aalto.fi/en/people/antti-oulasvirta | E99: Open related PDF / author profile | F99: Located - corrective source needed | G99: Exact row label is vague and may need replacement; accessible Oulasvirta UI-design source recorded as provisional offloading/interface-design anchor. | H99: Oulasvirta — offloading and interface design pdf DOI readable source | I99: https://www.google.com/search?q=Oulasvirta+%E2%80%94+offloading+and+interface+design+pdf+DOI+readable+source | J99: 2026-08-13 | K99: Pending | L99: 7 | M99: WS-H | N99: B | O99: DESIGN | P99: theoretical | Q99: HCI | R99: conceptual | S99: low | T99: Interface-level offloading considerations. | U99: [to chart] | V99: [to chart] | W99: [to chart] | X99: partial | Y99: partial | Z99: Interface offloading tradeoffs. | AA99: Design mediates offloading. | AC99: Digital Capture Architecture | AE99: Empirical / applied research | AF99: 24 months | AG99: 2026-08-13 | AH99: 2028-08-13 | AI99: Current - located, access/fit caveat
A100: A7-10 | B100: Recent GenAI & perceived self-regulated learning (empirical) | C100: https://www.nature.com/articles/s41599-026-07924-3.pdf | D100: https://arxiv.org/pdf/2606.08568 | E100: Open article PDF / arXiv preprint | F100: Located - readable source | G100: Recent 2026 GenAI/SRL sources located; fast-moving row should be re-searched frequently. | H100: Recent GenAI & perceived self-regulated learning (empirical) pdf DOI readable source | I100: https://www.google.com/search?q=Recent+GenAI+%26+perceived+self-regulated+learning+%28empirical%29+pdf+DOI+readable+source | J100: 2026-08-13 | K100: Pending | L100: 7 | M100: WS-H | N100: B | O100: EMPIRICAL/WARNING | P100: empirical | Q100: education/AI | R100: contested | S100: medium | T100: GenAI tool use associated with shifts in self-regulated learning. | U100: [to chart] | V100: [to chart] | W100: [to chart] | X100: partial | Y100: yes | Z100: Fast-moving; re-search each cycle. | AA100: Watch for dependency signals. | AB100: CF-3 | AC100: AI Assistant Use Rules | AD100: OC-13 | AE100: Fast-moving digital/AI/work trend | AF100: 6 months | AG100: 2026-08-13 | AH100: 2027-02-13 | AI100: Current - re-search on schedule
...

Sheet Source Patch Log
A1: Patch Date | B1: Patch Type | C1: Rows Updated | D1: Columns Added | E1: Rows Removed | F1: Existing Source Cells Removed | G1: Notes
A2: 2026-08-13 | B2: Additive patch | C2: 38 | D2: Staleness Domain, Re-search Interval, Last Verified Date, Re-search By, Staleness Status | E2: 0 | F2: 0 | G2: Patched staleness columns at workbook end and completed source-location pass for all previously queued/missing rows. Existing source links were preserved; only queued rows were filled.
A3: 2026-08-13 | B3: Source rows completed | C3: A1-15, A1-16, A1-17, A1-18, A1-19, A3-07, A3-08, A3-09, A3-10, A4-07, A4-08, A4-09, A4-10, A5-07, A5-08, A5-09, A5-10, A6-07, A6-08, A6-09, A6-10, A7-07, A7-08, A7-09, A7-10, A8-07, A8-08, A8-09, A8-10, A9-07, A9-08, A9-09, A9-10, A9-11, A10-05, A10-06, A10-07, A10-08 | G3: Rows were source-located, not evidentially charted. Citation is still not evidence.
